{
  "symbol": "ETHT",
  "createdAt": "2026-02-09T06:26:42.5071174Z",
  "updatedAt": "2026-02-09T06:26:42.6232095Z",
  "backtestStartDate": "2026-01-05T19:53:00",
  "backtestEndDate": "2026-02-06T19:59:00",
  "backtestDays": 24,
  "recentTrades": [
    {
      "entryTime": "2026-01-06T13:01:00",
      "exitTime": "2026-01-06T13:04:00",
      "entryPrice": 43.23,
      "exitPrice": 43.45,
      "isLong": false,
      "quantity": 100,
      "entryScore": -53,
      "entryVwapScore": -76,
      "entryEmaScore": -100,
      "entryRsiScore": -42,
      "entryMacdScore": -100,
      "entryAdxScore": -91,
      "entryVolumeScore": 0,
      "rsiAtEntry": 42.48008466913698,
      "adxAtEntry": 43.887243122640605,
      "entryBollingerScore": 0,
      "entryStochasticScore": 0,
      "entryObvScore": 0,
      "entryCciScore": 0,
      "entryWilliamsRScore": 0,
      "entrySentimentScore": 0,
      "entrySentimentConfidence": 0,
      "macdHistogramAtEntry": 0,
      "volumeRatioAtEntry": 0,
      "aboveVwapAtEntry": false,
      "aboveEma9AtEntry": false,
      "aboveEma21AtEntry": false,
      "exitScore": -36,
      "rsiAtExit": 42.48008466913698,
      "adxAtExit": 43.887243122640605,
      "exitReason": "reversal",
      "pnL": -22.000000000000597,
      "pnLPercent": -0.5089058524173167,
      "isWin": false,
      "duration": "00:03:00",
      "entryHour": 13,
      "entryMinute": 1,
      "timeBucket": "13:00"
    },
    {
      "entryTime": "2026-01-06T13:05:00",
      "exitTime": "2026-01-06T13:07:00",
      "entryPrice": 43.4,
      "exitPrice": 43.67,
      "isLong": false,
      "quantity": 100,
      "entryScore": -52,
      "entryVwapScore": -68,
      "entryEmaScore": -33,
      "entryRsiScore": -22,
      "entryMacdScore": -100,
      "entryAdxScore": -86,
      "entryVolumeScore": 0,
      "rsiAtEntry": 50.51807787224395,
      "adxAtEntry": 39.760070492930666,
      "entryBollingerScore": 0,
      "entryStochasticScore": 0,
      "entryObvScore": 0,
      "entryCciScore": 0,
      "entryWilliamsRScore": 0,
      "entrySentimentScore": 0,
      "entrySentimentConfidence": 0,
      "macdHistogramAtEntry": 0,
      "volumeRatioAtEntry": 0,
      "aboveVwapAtEntry": false,
      "aboveEma9AtEntry": false,
      "aboveEma21AtEntry": false,
      "exitScore": -25,
      "rsiAtExit": 50.51807787224395,
      "adxAtExit": 39.760070492930666,
      "exitReason": "reversal",
      "pnL": -27.000000000000313,
      "pnLPercent": -0.6221198156682101,
      "isWin": false,
      "duration": "00:02:00",
      "entryHour": 13,
      "entryMinute": 5,
      "timeBucket": "13:00"
    },
    {
      "entryTime": "2026-01-07T09:31:00",
      "exitTime": "2026-01-07T09:41:00",
      "entryPrice": 42.57,
      "exitPrice": 43.20170757585738,
      "isLong": false,
      "quantity": 100,
      "entryScore": -60,
      "entryVwapScore": -95,
      "entryEmaScore": -100,
      "entryRsiScore": 28,
      "entryMacdScore": -100,
      "entryAdxScore": -89,
      "entryVolumeScore": -100,
      "rsiAtEntry": 55.88844121812668,
      "adxAtEntry": 36.36277918634072,
      "entryBollingerScore": 0,
      "entryStochasticScore": 0,
      "entryObvScore": 0,
      "entryCciScore": 0,
      "entryWilliamsRScore": 0,
      "entrySentimentScore": 0,
      "entrySentimentConfidence": 0,
      "macdHistogramAtEntry": 0,
      "volumeRatioAtEntry": 0,
      "aboveVwapAtEntry": false,
      "aboveEma9AtEntry": false,
      "aboveEma21AtEntry": false,
      "exitScore": 3,
      "rsiAtExit": 55.88844121812668,
      "adxAtExit": 36.36277918634072,
      "exitReason": "SL",
      "pnL": -63.17075758573765,
      "pnLPercent": -1.483926652237201,
      "isWin": false,
      "duration": "00:10:00",
      "entryHour": 9,
      "entryMinute": 31,
      "timeBucket": "09:30"
    },
    {
      "entryTime": "2026-01-07T10:13:00",
      "exitTime": "2026-01-07T10:35:00",
      "entryPrice": 42.28,
      "exitPrice": 42.03,
      "isLong": false,
      "quantity": 100,
      "entryScore": -63,
      "entryVwapScore": -97,
      "entryEmaScore": -100,
      "entryRsiScore": -28,
      "entryMacdScore": -100,
      "entryAdxScore": -51,
      "entryVolumeScore": -14,
      "rsiAtEntry": 48.87046658761413,
      "adxAtEntry": 27.362278762262253,
      "entryBollingerScore": 0,
      "entryStochasticScore": 0,
      "entryObvScore": 0,
      "entryCciScore": 0,
      "entryWilliamsRScore": 0,
      "entrySentimentScore": 0,
      "entrySentimentConfidence": 0,
      "macdHistogramAtEntry": 0,
      "volumeRatioAtEntry": 0,
      "aboveVwapAtEntry": false,
      "aboveEma9AtEntry": false,
      "aboveEma21AtEntry": false,
      "exitScore": -22,
      "rsiAtExit": 48.87046658761413,
      "adxAtExit": 27.362278762262253,
      "exitReason": "reversal",
      "pnL": 25,
      "pnLPercent": 0.5912961210974457,
      "isWin": true,
      "duration": "00:22:00",
      "entryHour": 10,
      "entryMinute": 13,
      "timeBucket": "10:00"
    },
    {
      "entryTime": "2026-01-07T12:57:00",
      "exitTime": "2026-01-07T13:13:00",
      "entryPrice": 41.77,
      "exitPrice": 41.87,
      "isLong": false,
      "quantity": 100,
      "entryScore": -65,
      "entryVwapScore": -100,
      "entryEmaScore": -100,
      "entryRsiScore": -35,
      "entryMacdScore": -100,
      "entryAdxScore": -59,
      "entryVolumeScore": 0,
      "rsiAtEntry": 53.67232900876563,
      "adxAtEntry": 30.39414807603486,
      "entryBollingerScore": 0,
      "entryStochasticScore": 0,
      "entryObvScore": 0,
      "entryCciScore": 0,
      "entryWilliamsRScore": 0,
      "entrySentimentScore": 0,
      "entrySentimentConfidence": 0,
      "macdHistogramAtEntry": 0,
      "volumeRatioAtEntry": 0,
      "aboveVwapAtEntry": false,
      "aboveEma9AtEntry": false,
      "aboveEma21AtEntry": false,
      "exitScore": -27,
      "rsiAtExit": 53.67232900876563,
      "adxAtExit": 30.39414807603486,
      "exitReason": "reversal",
      "pnL": -9.999999999999432,
      "pnLPercent": -0.23940627244432444,
      "isWin": false,
      "duration": "00:16:00",
      "entryHour": 12,
      "entryMinute": 57,
      "timeBucket": "12:45"
    },
    {
      "entryTime": "2026-01-07T15:28:00",
      "exitTime": "2026-01-07T15:31:00",
      "entryPrice": 41.21,
      "exitPrice": 41.35,
      "isLong": false,
      "quantity": 100,
      "entryScore": -61,
      "entryVwapScore": -100,
      "entryEmaScore": -100,
      "entryRsiScore": -32,
      "entryMacdScore": -100,
      "entryAdxScore": -50,
      "entryVolumeScore": 0,
      "rsiAtEntry": 47.68640618013243,
      "adxAtEntry": 23.40505790406351,
      "entryBollingerScore": 0,
      "entryStochasticScore": 0,
      "entryObvScore": 0,
      "entryCciScore": 0,
      "entryWilliamsRScore": 0,
      "entrySentimentScore": 0,
      "entrySentimentConfidence": 0,
      "macdHistogramAtEntry": 0,
      "volumeRatioAtEntry": 0,
      "aboveVwapAtEntry": false,
      "aboveEma9AtEntry": false,
      "aboveEma21AtEntry": false,
      "exitScore": -32,
      "rsiAtExit": 47.68640618013243,
      "adxAtExit": 23.40505790406351,
      "exitReason": "reversal",
      "pnL": -14.000000000000057,
      "pnLPercent": -0.3397233681145367,
      "isWin": false,
      "duration": "00:03:00",
      "entryHour": 15,
      "entryMinute": 28,
      "timeBucket": "15:15"
    },
    {
      "entryTime": "2026-01-08T09:37:00",
      "exitTime": "2026-01-08T09:47:00",
      "entryPrice": 39.63,
      "exitPrice": 39.71,
      "isLong": false,
      "quantity": 100,
      "entryScore": -63,
      "entryVwapScore": -100,
      "entryEmaScore": -100,
      "entryRsiScore": -23,
      "entryMacdScore": -100,
      "entryAdxScore": -61,
      "entryVolumeScore": 0,
      "rsiAtEntry": 52.44655156220325,
      "adxAtEntry": 29.592883556717165,
      "entryBollingerScore": 0,
      "entryStochasticScore": 0,
      "entryObvScore": 0,
      "entryCciScore": 0,
      "entryWilliamsRScore": 0,
      "entrySentimentScore": 0,
      "entrySentimentConfidence": 0,
      "macdHistogramAtEntry": 0,
      "volumeRatioAtEntry": 0,
      "aboveVwapAtEntry": false,
      "aboveEma9AtEntry": false,
      "aboveEma21AtEntry": false,
      "exitScore": -23,
      "rsiAtExit": 52.44655156220325,
      "adxAtExit": 29.592883556717165,
      "exitReason": "reversal",
      "pnL": -7.9999999999998295,
      "pnLPercent": -0.20186727226847914,
      "isWin": false,
      "duration": "00:10:00",
      "entryHour": 9,
      "entryMinute": 37,
      "timeBucket": "09:30"
    },
    {
      "entryTime": "2026-01-08T15:11:00",
      "exitTime": "2026-01-08T15:31:00",
      "entryPrice": 40.17,
      "exitPrice": 40.31,
      "isLong": false,
      "quantity": 100,
      "entryScore": -69,
      "entryVwapScore": -100,
      "entryEmaScore": -100,
      "entryRsiScore": -46,
      "entryMacdScore": -100,
      "entryAdxScore": -78,
      "entryVolumeScore": 0,
      "rsiAtEntry": 51.52069226472449,
      "adxAtEntry": 19.65882838968962,
      "entryBollingerScore": 0,
      "entryStochasticScore": 0,
      "entryObvScore": 0,
      "entryCciScore": 0,
      "entryWilliamsRScore": 0,
      "entrySentimentScore": 0,
      "entrySentimentConfidence": 0,
      "macdHistogramAtEntry": 0,
      "volumeRatioAtEntry": 0,
      "aboveVwapAtEntry": false,
      "aboveEma9AtEntry": false,
      "aboveEma21AtEntry": false,
      "exitScore": -3,
      "rsiAtExit": 51.52069226472449,
      "adxAtExit": 19.65882838968962,
      "exitReason": "reversal",
      "pnL": -14.000000000000057,
      "pnLPercent": -0.34851879512073825,
      "isWin": false,
      "duration": "00:20:00",
      "entryHour": 15,
      "entryMinute": 11,
      "timeBucket": "15:00"
    },
    {
      "entryTime": "2026-01-09T09:40:00",
      "exitTime": "2026-01-09T09:59:00",
      "entryPrice": 39.75,
      "exitPrice": 39.74,
      "isLong": false,
      "quantity": 100,
      "entryScore": -66,
      "entryVwapScore": -100,
      "entryEmaScore": -100,
      "entryRsiScore": -32,
      "entryMacdScore": -91,
      "entryAdxScore": -37,
      "entryVolumeScore": -100,
      "rsiAtEntry": 52.71516367319252,
      "adxAtEntry": 22.42912096792162,
      "entryBollingerScore": 0,
      "entryStochasticScore": 0,
      "entryObvScore": 0,
      "entryCciScore": 0,
      "entryWilliamsRScore": 0,
      "entrySentimentScore": 0,
      "entrySentimentConfidence": 0,
      "macdHistogramAtEntry": 0,
      "volumeRatioAtEntry": 0,
      "aboveVwapAtEntry": false,
      "aboveEma9AtEntry": false,
      "aboveEma21AtEntry": false,
      "exitScore": -9,
      "rsiAtExit": 52.71516367319252,
      "adxAtExit": 22.42912096792162,
      "exitReason": "reversal",
      "pnL": 0.999999999999801,
      "pnLPercent": 0.02515723270439751,
      "isWin": true,
      "duration": "00:19:00",
      "entryHour": 9,
      "entryMinute": 40,
      "timeBucket": "09:30"
    },
    {
      "entryTime": "2026-01-09T12:26:00",
      "exitTime": "2026-01-09T12:38:00",
      "entryPrice": 40.72,
      "exitPrice": 40.62,
      "isLong": false,
      "quantity": 100,
      "entryScore": -61,
      "entryVwapScore": -71,
      "entryEmaScore": -100,
      "entryRsiScore": -25,
      "entryMacdScore": -100,
      "entryAdxScore": -70,
      "entryVolumeScore": -1,
      "rsiAtEntry": 43.29427984832594,
      "adxAtEntry": 32.35162036195093,
      "entryBollingerScore": 0,
      "entryStochasticScore": 0,
      "entryObvScore": 0,
      "entryCciScore": 0,
      "entryWilliamsRScore": 0,
      "entrySentimentScore": 0,
      "entrySentimentConfidence": 0,
      "macdHistogramAtEntry": 0,
      "volumeRatioAtEntry": 0,
      "aboveVwapAtEntry": false,
      "aboveEma9AtEntry": false,
      "aboveEma21AtEntry": false,
      "exitScore": -34,
      "rsiAtExit": 43.29427984832594,
      "adxAtExit": 32.35162036195093,
      "exitReason": "reversal",
      "pnL": 10.000000000000142,
      "pnLPercent": 0.2455795677799642,
      "isWin": true,
      "duration": "00:12:00",
      "entryHour": 12,
      "entryMinute": 26,
      "timeBucket": "12:15"
    },
    {
      "entryTime": "2026-01-09T14:18:00",
      "exitTime": "2026-01-09T14:39:00",
      "entryPrice": 39.78,
      "exitPrice": 39.69,
      "isLong": false,
      "quantity": 100,
      "entryScore": -66,
      "entryVwapScore": -100,
      "entryEmaScore": -100,
      "entryRsiScore": -37,
      "entryMacdScore": -100,
      "entryAdxScore": -66,
      "entryVolumeScore": -89,
      "rsiAtEntry": 48.01365447509785,
      "adxAtEntry": 44.29234238954384,
      "entryBollingerScore": 0,
      "entryStochasticScore": 0,
      "entryObvScore": 0,
      "entryCciScore": 0,
      "entryWilliamsRScore": 0,
      "entrySentimentScore": 0,
      "entrySentimentConfidence": 0,
      "macdHistogramAtEntry": 0,
      "volumeRatioAtEntry": 0,
      "aboveVwapAtEntry": false,
      "aboveEma9AtEntry": false,
      "aboveEma21AtEntry": false,
      "exitScore": -28,
      "rsiAtExit": 48.01365447509785,
      "adxAtExit": 44.29234238954384,
      "exitReason": "reversal",
      "pnL": 9.000000000000341,
      "pnLPercent": 0.2262443438914113,
      "isWin": true,
      "duration": "00:21:00",
      "entryHour": 14,
      "entryMinute": 18,
      "timeBucket": "14:15"
    },
    {
      "entryTime": "2026-01-09T15:55:00",
      "exitTime": "2026-01-09T16:09:00",
      "entryPrice": 39.62,
      "exitPrice": 39.68,
      "isLong": false,
      "quantity": 100,
      "entryScore": -60,
      "entryVwapScore": -100,
      "entryEmaScore": -100,
      "entryRsiScore": -48,
      "entryMacdScore": -95,
      "entryAdxScore": -69,
      "entryVolumeScore": 0,
      "rsiAtEntry": 54.04538838651649,
      "adxAtEntry": 40.21480088537193,
      "entryBollingerScore": 0,
      "entryStochasticScore": 0,
      "entryObvScore": 0,
      "entryCciScore": 0,
      "entryWilliamsRScore": 0,
      "entrySentimentScore": 0,
      "entrySentimentConfidence": 0,
      "macdHistogramAtEntry": 0,
      "volumeRatioAtEntry": 0,
      "aboveVwapAtEntry": false,
      "aboveEma9AtEntry": false,
      "aboveEma21AtEntry": false,
      "exitScore": -7,
      "rsiAtExit": 54.04538838651649,
      "adxAtExit": 40.21480088537193,
      "exitReason": "reversal",
      "pnL": -6.000000000000227,
      "pnLPercent": -0.15143866733973316,
      "isWin": false,
      "duration": "00:14:00",
      "entryHour": 15,
      "entryMinute": 55,
      "timeBucket": "15:45"
    },
    {
      "entryTime": "2026-01-12T12:38:00",
      "exitTime": "2026-01-12T12:49:00",
      "entryPrice": 40.17,
      "exitPrice": 40.38,
      "isLong": false,
      "quantity": 100,
      "entryScore": -65,
      "entryVwapScore": -76,
      "entryEmaScore": -100,
      "entryRsiScore": 17,
      "entryMacdScore": -100,
      "entryAdxScore": -98,
      "entryVolumeScore": -100,
      "rsiAtEntry": 48.04276300394179,
      "adxAtEntry": 35.81913786733178,
      "entryBollingerScore": 0,
      "entryStochasticScore": 0,
      "entryObvScore": 0,
      "entryCciScore": 0,
      "entryWilliamsRScore": 0,
      "entrySentimentScore": 0,
      "entrySentimentConfidence": 0,
      "macdHistogramAtEntry": 0,
      "volumeRatioAtEntry": 0,
      "aboveVwapAtEntry": false,
      "aboveEma9AtEntry": false,
      "aboveEma21AtEntry": false,
      "exitScore": -12,
      "rsiAtExit": 48.04276300394179,
      "adxAtExit": 35.81913786733178,
      "exitReason": "reversal",
      "pnL": -21.000000000000085,
      "pnLPercent": -0.5227781926811074,
      "isWin": false,
      "duration": "00:11:00",
      "entryHour": 12,
      "entryMinute": 38,
      "timeBucket": "12:30"
    },
    {
      "entryTime": "2026-01-14T11:39:00",
      "exitTime": "2026-01-14T11:43:00",
      "entryPrice": 48.2,
      "exitPrice": 48.1,
      "isLong": true,
      "quantity": 100,
      "entryScore": 65,
      "entryVwapScore": 100,
      "entryEmaScore": 100,
      "entryRsiScore": 39,
      "entryMacdScore": 53,
      "entryAdxScore": 70,
      "entryVolumeScore": 100,
      "rsiAtEntry": 61.19133509717714,
      "adxAtEntry": 36.36066122285105,
      "entryBollingerScore": 0,
      "entryStochasticScore": 0,
      "entryObvScore": 0,
      "entryCciScore": 0,
      "entryWilliamsRScore": 0,
      "entrySentimentScore": 0,
      "entrySentimentConfidence": 0,
      "macdHistogramAtEntry": 0,
      "volumeRatioAtEntry": 0,
      "aboveVwapAtEntry": false,
      "aboveEma9AtEntry": false,
      "aboveEma21AtEntry": false,
      "exitScore": 37,
      "rsiAtExit": 61.19133509717714,
      "adxAtExit": 36.36066122285105,
      "exitReason": "reversal",
      "pnL": -10.000000000000142,
      "pnLPercent": -0.20746887966805275,
      "isWin": false,
      "duration": "00:04:00",
      "entryHour": 11,
      "entryMinute": 39,
      "timeBucket": "11:30"
    },
    {
      "entryTime": "2026-01-14T14:28:00",
      "exitTime": "2026-01-14T14:35:00",
      "entryPrice": 47.46,
      "exitPrice": 47.56,
      "isLong": true,
      "quantity": 100,
      "entryScore": 64,
      "entryVwapScore": 100,
      "entryEmaScore": 100,
      "entryRsiScore": 49,
      "entryMacdScore": 57,
      "entryAdxScore": 86,
      "entryVolumeScore": 100,
      "rsiAtEntry": 57.761397963147175,
      "adxAtEntry": 51.255147045681916,
      "entryBollingerScore": 0,
      "entryStochasticScore": 0,
      "entryObvScore": 0,
      "entryCciScore": 0,
      "entryWilliamsRScore": 0,
      "entrySentimentScore": 0,
      "entrySentimentConfidence": 0,
      "macdHistogramAtEntry": 0,
      "volumeRatioAtEntry": 0,
      "aboveVwapAtEntry": false,
      "aboveEma9AtEntry": false,
      "aboveEma21AtEntry": false,
      "exitScore": 19,
      "rsiAtExit": 57.761397963147175,
      "adxAtExit": 51.255147045681916,
      "exitReason": "reversal",
      "pnL": 10.000000000000142,
      "pnLPercent": 0.21070375052676238,
      "isWin": true,
      "duration": "00:07:00",
      "entryHour": 14,
      "entryMinute": 28,
      "timeBucket": "14:15"
    },
    {
      "entryTime": "2026-01-20T09:30:00",
      "exitTime": "2026-01-20T09:39:00",
      "entryPrice": 38.79,
      "exitPrice": 39.18,
      "isLong": false,
      "quantity": 100,
      "entryScore": -66,
      "entryVwapScore": -100,
      "entryEmaScore": -100,
      "entryRsiScore": -25,
      "entryMacdScore": -100,
      "entryAdxScore": -63,
      "entryVolumeScore": -100,
      "rsiAtEntry": 61.11508351091293,
      "adxAtEntry": 26.666054815187113,
      "entryBollingerScore": 0,
      "entryStochasticScore": 0,
      "entryObvScore": 0,
      "entryCciScore": 0,
      "entryWilliamsRScore": 0,
      "entrySentimentScore": 0,
      "entrySentimentConfidence": 0,
      "macdHistogramAtEntry": 0,
      "volumeRatioAtEntry": 0,
      "aboveVwapAtEntry": false,
      "aboveEma9AtEntry": false,
      "aboveEma21AtEntry": false,
      "exitScore": -2,
      "rsiAtExit": 61.11508351091293,
      "adxAtExit": 26.666054815187113,
      "exitReason": "reversal",
      "pnL": -39.00000000000006,
      "pnLPercent": -1.0054137664346496,
      "isWin": false,
      "duration": "00:09:00",
      "entryHour": 9,
      "entryMinute": 30,
      "timeBucket": "09:30"
    },
    {
      "entryTime": "2026-01-20T10:01:00",
      "exitTime": "2026-01-20T10:09:00",
      "entryPrice": 38.02,
      "exitPrice": 36.92789221585535,
      "isLong": false,
      "quantity": 100,
      "entryScore": -65,
      "entryVwapScore": -100,
      "entryEmaScore": -100,
      "entryRsiScore": -34,
      "entryMacdScore": -100,
      "entryAdxScore": -37,
      "entryVolumeScore": -60,
      "rsiAtEntry": 19.91131970148311,
      "adxAtEntry": 34.714647169129314,
      "entryBollingerScore": 0,
      "entryStochasticScore": 0,
      "entryObvScore": 0,
      "entryCciScore": 0,
      "entryWilliamsRScore": 0,
      "entrySentimentScore": 0,
      "entrySentimentConfidence": 0,
      "macdHistogramAtEntry": 0,
      "volumeRatioAtEntry": 0,
      "aboveVwapAtEntry": false,
      "aboveEma9AtEntry": false,
      "aboveEma21AtEntry": false,
      "exitScore": -52,
      "rsiAtExit": 19.91131970148311,
      "adxAtExit": 34.714647169129314,
      "exitReason": "TP",
      "pnL": 109.21077841446518,
      "pnLPercent": 2.8724560340469534,
      "isWin": true,
      "duration": "00:08:00",
      "entryHour": 10,
      "entryMinute": 1,
      "timeBucket": "10:00"
    },
    {
      "entryTime": "2026-01-20T10:14:00",
      "exitTime": "2026-01-20T10:17:00",
      "entryPrice": 37.41,
      "exitPrice": 37.49,
      "isLong": false,
      "quantity": 100,
      "entryScore": -65,
      "entryVwapScore": -100,
      "entryEmaScore": -100,
      "entryRsiScore": -27,
      "entryMacdScore": -100,
      "entryAdxScore": -72,
      "entryVolumeScore": 0,
      "rsiAtEntry": 43.31629946363923,
      "adxAtEntry": 34.7560493274405,
      "entryBollingerScore": 0,
      "entryStochasticScore": 0,
      "entryObvScore": 0,
      "entryCciScore": 0,
      "entryWilliamsRScore": 0,
      "entrySentimentScore": 0,
      "entrySentimentConfidence": 0,
      "macdHistogramAtEntry": 0,
      "volumeRatioAtEntry": 0,
      "aboveVwapAtEntry": false,
      "aboveEma9AtEntry": false,
      "aboveEma21AtEntry": false,
      "exitScore": -37,
      "rsiAtExit": 43.31629946363923,
      "adxAtExit": 34.7560493274405,
      "exitReason": "reversal",
      "pnL": -8.00000000000054,
      "pnLPercent": -0.21384656508956268,
      "isWin": false,
      "duration": "00:03:00",
      "entryHour": 10,
      "entryMinute": 14,
      "timeBucket": "10:00"
    },
    {
      "entryTime": "2026-01-20T11:52:00",
      "exitTime": "2026-01-20T11:56:00",
      "entryPrice": 37.1,
      "exitPrice": 37.17,
      "isLong": false,
      "quantity": 100,
      "entryScore": -60,
      "entryVwapScore": -100,
      "entryEmaScore": -100,
      "entryRsiScore": -30,
      "entryMacdScore": -100,
      "entryAdxScore": -67,
      "entryVolumeScore": 0,
      "rsiAtEntry": 45.2843267588993,
      "adxAtEntry": 28.14372772374063,
      "entryBollingerScore": 0,
      "entryStochasticScore": 0,
      "entryObvScore": 0,
      "entryCciScore": 0,
      "entryWilliamsRScore": 0,
      "entrySentimentScore": 0,
      "entrySentimentConfidence": 0,
      "macdHistogramAtEntry": 0,
      "volumeRatioAtEntry": 0,
      "aboveVwapAtEntry": false,
      "aboveEma9AtEntry": false,
      "aboveEma21AtEntry": false,
      "exitScore": -37,
      "rsiAtExit": 45.2843267588993,
      "adxAtExit": 28.14372772374063,
      "exitReason": "reversal",
      "pnL": -7.000000000000028,
      "pnLPercent": -0.18867924528301963,
      "isWin": false,
      "duration": "00:04:00",
      "entryHour": 11,
      "entryMinute": 52,
      "timeBucket": "11:45"
    },
    {
      "entryTime": "2026-01-20T12:39:00",
      "exitTime": "2026-01-20T12:42:00",
      "entryPrice": 36.74,
      "exitPrice": 36.9,
      "isLong": false,
      "quantity": 100,
      "entryScore": -66,
      "entryVwapScore": -100,
      "entryEmaScore": -100,
      "entryRsiScore": -30,
      "entryMacdScore": -100,
      "entryAdxScore": -85,
      "entryVolumeScore": -43,
      "rsiAtEntry": 46.70000466222712,
      "adxAtEntry": 39.512746216462645,
      "entryBollingerScore": 0,
      "entryStochasticScore": 0,
      "entryObvScore": 0,
      "entryCciScore": 0,
      "entryWilliamsRScore": 0,
      "entrySentimentScore": 0,
      "entrySentimentConfidence": 0,
      "macdHistogramAtEntry": 0,
      "volumeRatioAtEntry": 0,
      "aboveVwapAtEntry": false,
      "aboveEma9AtEntry": false,
      "aboveEma21AtEntry": false,
      "exitScore": -38,
      "rsiAtExit": 46.70000466222712,
      "adxAtExit": 39.512746216462645,
      "exitReason": "reversal",
      "pnL": -15.999999999999659,
      "pnLPercent": -0.43549265106150403,
      "isWin": false,
      "duration": "00:03:00",
      "entryHour": 12,
      "entryMinute": 39,
      "timeBucket": "12:30"
    },
    {
      "entryTime": "2026-01-20T12:45:00",
      "exitTime": "2026-01-20T12:49:00",
      "entryPrice": 36.81,
      "exitPrice": 36.9,
      "isLong": false,
      "quantity": 100,
      "entryScore": -63,
      "entryVwapScore": -100,
      "entryEmaScore": -100,
      "entryRsiScore": -17,
      "entryMacdScore": -100,
      "entryAdxScore": -71,
      "entryVolumeScore": 0,
      "rsiAtEntry": 50.360629630792246,
      "adxAtEntry": 32.63958560563852,
      "entryBollingerScore": 0,
      "entryStochasticScore": 0,
      "entryObvScore": 0,
      "entryCciScore": 0,
      "entryWilliamsRScore": 0,
      "entrySentimentScore": 0,
      "entrySentimentConfidence": 0,
      "macdHistogramAtEntry": 0,
      "volumeRatioAtEntry": 0,
      "aboveVwapAtEntry": false,
      "aboveEma9AtEntry": false,
      "aboveEma21AtEntry": false,
      "exitScore": -26,
      "rsiAtExit": 50.360629630792246,
      "adxAtExit": 32.63958560563852,
      "exitReason": "reversal",
      "pnL": -8.99999999999963,
      "pnLPercent": -0.2444987775061024,
      "isWin": false,
      "duration": "00:04:00",
      "entryHour": 12,
      "entryMinute": 45,
      "timeBucket": "12:45"
    },
    {
      "entryTime": "2026-01-20T12:50:00",
      "exitTime": "2026-01-20T12:54:00",
      "entryPrice": 36.75,
      "exitPrice": 37.02,
      "isLong": false,
      "quantity": 100,
      "entryScore": -61,
      "entryVwapScore": -100,
      "entryEmaScore": -100,
      "entryRsiScore": -13,
      "entryMacdScore": -100,
      "entryAdxScore": -62,
      "entryVolumeScore": 0,
      "rsiAtEntry": 56.157782180069724,
      "adxAtEntry": 26.733343322303828,
      "entryBollingerScore": 0,
      "entryStochasticScore": 0,
      "entryObvScore": 0,
      "entryCciScore": 0,
      "entryWilliamsRScore": 0,
      "entrySentimentScore": 0,
      "entrySentimentConfidence": 0,
      "macdHistogramAtEntry": 0,
      "volumeRatioAtEntry": 0,
      "aboveVwapAtEntry": false,
      "aboveEma9AtEntry": false,
      "aboveEma21AtEntry": false,
      "exitScore": 0,
      "rsiAtExit": 56.157782180069724,
      "adxAtExit": 26.733343322303828,
      "exitReason": "reversal",
      "pnL": -27.000000000000313,
      "pnLPercent": -0.734693877551029,
      "isWin": false,
      "duration": "00:04:00",
      "entryHour": 12,
      "entryMinute": 50,
      "timeBucket": "12:45"
    },
    {
      "entryTime": "2026-01-21T11:29:00",
      "exitTime": "2026-01-21T11:40:00",
      "entryPrice": 35.99,
      "exitPrice": 34.84303279614704,
      "isLong": false,
      "quantity": 100,
      "entryScore": -67,
      "entryVwapScore": -100,
      "entryEmaScore": -100,
      "entryRsiScore": -32,
      "entryMacdScore": -100,
      "entryAdxScore": -70,
      "entryVolumeScore": -19,
      "rsiAtEntry": 19.5539767237416,
      "adxAtEntry": 50.22761757284355,
      "entryBollingerScore": 0,
      "entryStochasticScore": 0,
      "entryObvScore": 0,
      "entryCciScore": 0,
      "entryWilliamsRScore": 0,
      "entrySentimentScore": 0,
      "entrySentimentConfidence": 0,
      "macdHistogramAtEntry": 0,
      "volumeRatioAtEntry": 0,
      "aboveVwapAtEntry": false,
      "aboveEma9AtEntry": false,
      "aboveEma21AtEntry": false,
      "exitScore": -58,
      "rsiAtExit": 19.5539767237416,
      "adxAtExit": 50.22761757284355,
      "exitReason": "TP",
      "pnL": 114.69672038529595,
      "pnLPercent": 3.186905262164377,
      "isWin": true,
      "duration": "00:11:00",
      "entryHour": 11,
      "entryMinute": 29,
      "timeBucket": "11:15"
    },
    {
      "entryTime": "2026-01-21T11:45:00",
      "exitTime": "2026-01-21T12:20:00",
      "entryPrice": 34.55,
      "exitPrice": 34.36,
      "isLong": false,
      "quantity": 100,
      "entryScore": -58,
      "entryVwapScore": -100,
      "entryEmaScore": -100,
      "entryRsiScore": 1,
      "entryMacdScore": -100,
      "entryAdxScore": -100,
      "entryVolumeScore": -98,
      "rsiAtEntry": 48.9854973848442,
      "adxAtEntry": 33.571533694307895,
      "entryBollingerScore": 0,
      "entryStochasticScore": 0,
      "entryObvScore": 0,
      "entryCciScore": 0,
      "entryWilliamsRScore": 0,
      "entrySentimentScore": 0,
      "entrySentimentConfidence": 0,
      "macdHistogramAtEntry": 0,
      "volumeRatioAtEntry": 0,
      "aboveVwapAtEntry": false,
      "aboveEma9AtEntry": false,
      "aboveEma21AtEntry": false,
      "exitScore": -35,
      "rsiAtExit": 48.9854973848442,
      "adxAtExit": 33.571533694307895,
      "exitReason": "reversal",
      "pnL": 18.999999999999773,
      "pnLPercent": 0.5499276410998488,
      "isWin": true,
      "duration": "00:35:00",
      "entryHour": 11,
      "entryMinute": 45,
      "timeBucket": "11:45"
    },
    {
      "entryTime": "2026-01-21T12:22:00",
      "exitTime": "2026-01-21T12:39:00",
      "entryPrice": 34.19,
      "exitPrice": 34.19,
      "isLong": false,
      "quantity": 100,
      "entryScore": -62,
      "entryVwapScore": -100,
      "entryEmaScore": -100,
      "entryRsiScore": -13,
      "entryMacdScore": -100,
      "entryAdxScore": -63,
      "entryVolumeScore": 0,
      "rsiAtEntry": 49.917568457416806,
      "adxAtEntry": 22.06909027988296,
      "entryBollingerScore": 0,
      "entryStochasticScore": 0,
      "entryObvScore": 0,
      "entryCciScore": 0,
      "entryWilliamsRScore": 0,
      "entrySentimentScore": 0,
      "entrySentimentConfidence": 0,
      "macdHistogramAtEntry": 0,
      "volumeRatioAtEntry": 0,
      "aboveVwapAtEntry": false,
      "aboveEma9AtEntry": false,
      "aboveEma21AtEntry": false,
      "exitScore": -21,
      "rsiAtExit": 49.917568457416806,
      "adxAtExit": 22.06909027988296,
      "exitReason": "reversal",
      "pnL": 0,
      "pnLPercent": 0,
      "isWin": false,
      "duration": "00:17:00",
      "entryHour": 12,
      "entryMinute": 22,
      "timeBucket": "12:15"
    },
    {
      "entryTime": "2026-01-21T15:29:00",
      "exitTime": "2026-01-21T15:35:00",
      "entryPrice": 37.22,
      "exitPrice": 37.55,
      "isLong": false,
      "quantity": 100,
      "entryScore": -70,
      "entryVwapScore": -100,
      "entryEmaScore": -100,
      "entryRsiScore": -24,
      "entryMacdScore": -100,
      "entryAdxScore": -53,
      "entryVolumeScore": -100,
      "rsiAtEntry": 54.697565222475504,
      "adxAtEntry": 22.528746054745216,
      "entryBollingerScore": 0,
      "entryStochasticScore": 0,
      "entryObvScore": 0,
      "entryCciScore": 0,
      "entryWilliamsRScore": 0,
      "entrySentimentScore": 0,
      "entrySentimentConfidence": 0,
      "macdHistogramAtEntry": 0,
      "volumeRatioAtEntry": 0,
      "aboveVwapAtEntry": false,
      "aboveEma9AtEntry": false,
      "aboveEma21AtEntry": false,
      "exitScore": -29,
      "rsiAtExit": 54.697565222475504,
      "adxAtExit": 22.528746054745216,
      "exitReason": "reversal",
      "pnL": -32.99999999999983,
      "pnLPercent": -0.8866200967221879,
      "isWin": false,
      "duration": "00:06:00",
      "entryHour": 15,
      "entryMinute": 29,
      "timeBucket": "15:15"
    },
    {
      "entryTime": "2026-01-22T09:43:00",
      "exitTime": "2026-01-22T10:04:00",
      "entryPrice": 35.91,
      "exitPrice": 35.64,
      "isLong": false,
      "quantity": 100,
      "entryScore": -65,
      "entryVwapScore": -100,
      "entryEmaScore": -100,
      "entryRsiScore": -24,
      "entryMacdScore": -88,
      "entryAdxScore": -37,
      "entryVolumeScore": -100,
      "rsiAtEntry": 48.75741568471609,
      "adxAtEntry": 31.5854713826215,
      "entryBollingerScore": 0,
      "entryStochasticScore": 0,
      "entryObvScore": 0,
      "entryCciScore": 0,
      "entryWilliamsRScore": 0,
      "entrySentimentScore": 0,
      "entrySentimentConfidence": 0,
      "macdHistogramAtEntry": 0,
      "volumeRatioAtEntry": 0,
      "aboveVwapAtEntry": false,
      "aboveEma9AtEntry": false,
      "aboveEma21AtEntry": false,
      "exitScore": -27,
      "rsiAtExit": 48.75741568471609,
      "adxAtExit": 31.5854713826215,
      "exitReason": "reversal",
      "pnL": 26.999999999999602,
      "pnLPercent": 0.7518796992481094,
      "isWin": true,
      "duration": "00:21:00",
      "entryHour": 9,
      "entryMinute": 43,
      "timeBucket": "09:30"
    },
    {
      "entryTime": "2026-01-22T15:33:00",
      "exitTime": "2026-01-22T15:46:00",
      "entryPrice": 35.48,
      "exitPrice": 35.36,
      "isLong": false,
      "quantity": 100,
      "entryScore": -62,
      "entryVwapScore": -100,
      "entryEmaScore": -100,
      "entryRsiScore": -20,
      "entryMacdScore": -98,
      "entryAdxScore": -57,
      "entryVolumeScore": 0,
      "rsiAtEntry": 43.838312441393754,
      "adxAtEntry": 36.29741360495174,
      "entryBollingerScore": 0,
      "entryStochasticScore": 0,
      "entryObvScore": 0,
      "entryCciScore": 0,
      "entryWilliamsRScore": 0,
      "entrySentimentScore": 0,
      "entrySentimentConfidence": 0,
      "macdHistogramAtEntry": 0,
      "volumeRatioAtEntry": 0,
      "aboveVwapAtEntry": false,
      "aboveEma9AtEntry": false,
      "aboveEma21AtEntry": false,
      "exitScore": -37,
      "rsiAtExit": 43.838312441393754,
      "adxAtExit": 36.29741360495174,
      "exitReason": "reversal",
      "pnL": 11.999999999999744,
      "pnLPercent": 0.3382187147688767,
      "isWin": true,
      "duration": "00:13:00",
      "entryHour": 15,
      "entryMinute": 33,
      "timeBucket": "15:30"
    },
    {
      "entryTime": "2026-01-23T09:36:00",
      "exitTime": "2026-01-23T09:38:00",
      "entryPrice": 34.8,
      "exitPrice": 34.43834519484377,
      "isLong": false,
      "quantity": 100,
      "entryScore": -55,
      "entryVwapScore": -100,
      "entryEmaScore": -100,
      "entryRsiScore": 6,
      "entryMacdScore": -100,
      "entryAdxScore": -95,
      "entryVolumeScore": -100,
      "rsiAtEntry": 19.1443370884991,
      "adxAtEntry": 50.72023722566628,
      "entryBollingerScore": 0,
      "entryStochasticScore": 0,
      "entryObvScore": 0,
      "entryCciScore": 0,
      "entryWilliamsRScore": 0,
      "entrySentimentScore": 0,
      "entrySentimentConfidence": 0,
      "macdHistogramAtEntry": 0,
      "volumeRatioAtEntry": 0,
      "aboveVwapAtEntry": false,
      "aboveEma9AtEntry": false,
      "aboveEma21AtEntry": false,
      "exitScore": -55,
      "rsiAtExit": 19.1443370884991,
      "adxAtExit": 50.72023722566628,
      "exitReason": "TP",
      "pnL": 36.16548051562276,
      "pnLPercent": 1.0392379458512289,
      "isWin": true,
      "duration": "00:02:00",
      "entryHour": 9,
      "entryMinute": 36,
      "timeBucket": "09:30"
    },
    {
      "entryTime": "2026-01-23T09:40:00",
      "exitTime": "2026-01-23T09:52:00",
      "entryPrice": 34.61,
      "exitPrice": 34.78,
      "isLong": false,
      "quantity": 100,
      "entryScore": -54,
      "entryVwapScore": -100,
      "entryEmaScore": -100,
      "entryRsiScore": -32,
      "entryMacdScore": -100,
      "entryAdxScore": -100,
      "entryVolumeScore": 0,
      "rsiAtEntry": 50.3253729047542,
      "adxAtEntry": 40.57967439806299,
      "entryBollingerScore": 0,
      "entryStochasticScore": 0,
      "entryObvScore": 0,
      "entryCciScore": 0,
      "entryWilliamsRScore": 0,
      "entrySentimentScore": 0,
      "entrySentimentConfidence": 0,
      "macdHistogramAtEntry": 0,
      "volumeRatioAtEntry": 0,
      "aboveVwapAtEntry": false,
      "aboveEma9AtEntry": false,
      "aboveEma21AtEntry": false,
      "exitScore": -16,
      "rsiAtExit": 50.3253729047542,
      "adxAtExit": 40.57967439806299,
      "exitReason": "reversal",
      "pnL": -17.00000000000017,
      "pnLPercent": -0.4911875180583696,
      "isWin": false,
      "duration": "00:12:00",
      "entryHour": 9,
      "entryMinute": 40,
      "timeBucket": "09:30"
    },
    {
      "entryTime": "2026-01-23T14:24:00",
      "exitTime": "2026-01-23T14:57:00",
      "entryPrice": 36.12,
      "exitPrice": 35.83,
      "isLong": false,
      "quantity": 100,
      "entryScore": -62,
      "entryVwapScore": -100,
      "entryEmaScore": -100,
      "entryRsiScore": -24,
      "entryMacdScore": -100,
      "entryAdxScore": -55,
      "entryVolumeScore": 0,
      "rsiAtEntry": 50.88241717405342,
      "adxAtEntry": 28.111290391625744,
      "entryBollingerScore": 0,
      "entryStochasticScore": 0,
      "entryObvScore": 0,
      "entryCciScore": 0,
      "entryWilliamsRScore": 0,
      "entrySentimentScore": 0,
      "entrySentimentConfidence": 0,
      "macdHistogramAtEntry": 0,
      "volumeRatioAtEntry": 0,
      "aboveVwapAtEntry": false,
      "aboveEma9AtEntry": false,
      "aboveEma21AtEntry": false,
      "exitScore": -22,
      "rsiAtExit": 50.88241717405342,
      "adxAtExit": 28.111290391625744,
      "exitReason": "reversal",
      "pnL": 28.999999999999915,
      "pnLPercent": 0.8028792912513819,
      "isWin": true,
      "duration": "00:33:00",
      "entryHour": 14,
      "entryMinute": 24,
      "timeBucket": "14:15"
    },
    {
      "entryTime": "2026-01-23T15:35:00",
      "exitTime": "2026-01-23T16:01:00",
      "entryPrice": 35.37,
      "exitPrice": 35.44,
      "isLong": false,
      "quantity": 100,
      "entryScore": -56,
      "entryVwapScore": -100,
      "entryEmaScore": -100,
      "entryRsiScore": 1,
      "entryMacdScore": -100,
      "entryAdxScore": -86,
      "entryVolumeScore": -100,
      "rsiAtEntry": 50.39476026897234,
      "adxAtEntry": 39.594356289628266,
      "entryBollingerScore": 0,
      "entryStochasticScore": 0,
      "entryObvScore": 0,
      "entryCciScore": 0,
      "entryWilliamsRScore": 0,
      "entrySentimentScore": 0,
      "entrySentimentConfidence": 0,
      "macdHistogramAtEntry": 0,
      "volumeRatioAtEntry": 0,
      "aboveVwapAtEntry": false,
      "aboveEma9AtEntry": false,
      "aboveEma21AtEntry": false,
      "exitScore": -25,
      "rsiAtExit": 50.39476026897234,
      "adxAtExit": 39.594356289628266,
      "exitReason": "reversal",
      "pnL": -7.000000000000028,
      "pnLPercent": -0.19790783149561858,
      "isWin": false,
      "duration": "00:26:00",
      "entryHour": 15,
      "entryMinute": 35,
      "timeBucket": "15:30"
    },
    {
      "entryTime": "2026-01-26T09:30:00",
      "exitTime": "2026-01-26T09:34:00",
      "entryPrice": 33.97,
      "exitPrice": 34.39531311378946,
      "isLong": false,
      "quantity": 100,
      "entryScore": -61,
      "entryVwapScore": -100,
      "entryEmaScore": -100,
      "entryRsiScore": 8,
      "entryMacdScore": -100,
      "entryAdxScore": -94,
      "entryVolumeScore": -100,
      "rsiAtEntry": 66.80530880159118,
      "adxAtEntry": 46.87974199372392,
      "entryBollingerScore": 0,
      "entryStochasticScore": 0,
      "entryObvScore": 0,
      "entryCciScore": 0,
      "entryWilliamsRScore": 0,
      "entrySentimentScore": 0,
      "entrySentimentConfidence": 0,
      "macdHistogramAtEntry": 0,
      "volumeRatioAtEntry": 0,
      "aboveVwapAtEntry": false,
      "aboveEma9AtEntry": false,
      "aboveEma21AtEntry": false,
      "exitScore": 6,
      "rsiAtExit": 66.80530880159118,
      "adxAtExit": 46.87974199372392,
      "exitReason": "SL",
      "pnL": -42.53131137894641,
      "pnLPercent": -1.252025651426153,
      "isWin": false,
      "duration": "00:04:00",
      "entryHour": 9,
      "entryMinute": 30,
      "timeBucket": "09:30"
    },
    {
      "entryTime": "2026-01-26T10:39:00",
      "exitTime": "2026-01-26T10:56:00",
      "entryPrice": 34.72,
      "exitPrice": 34.5,
      "isLong": false,
      "quantity": 100,
      "entryScore": -61,
      "entryVwapScore": -100,
      "entryEmaScore": -100,
      "entryRsiScore": -27,
      "entryMacdScore": -100,
      "entryAdxScore": -60,
      "entryVolumeScore": -100,
      "rsiAtEntry": 48.28880690886248,
      "adxAtEntry": 30.65954442885224,
      "entryBollingerScore": 0,
      "entryStochasticScore": 0,
      "entryObvScore": 0,
      "entryCciScore": 0,
      "entryWilliamsRScore": 0,
      "entrySentimentScore": 0,
      "entrySentimentConfidence": 0,
      "macdHistogramAtEntry": 0,
      "volumeRatioAtEntry": 0,
      "aboveVwapAtEntry": false,
      "aboveEma9AtEntry": false,
      "aboveEma21AtEntry": false,
      "exitScore": -29,
      "rsiAtExit": 48.28880690886248,
      "adxAtExit": 30.65954442885224,
      "exitReason": "reversal",
      "pnL": 21.999999999999886,
      "pnLPercent": 0.6336405529953885,
      "isWin": true,
      "duration": "00:17:00",
      "entryHour": 10,
      "entryMinute": 39,
      "timeBucket": "10:30"
    },
    {
      "entryTime": "2026-01-26T10:57:00",
      "exitTime": "2026-01-26T11:04:00",
      "entryPrice": 34.43,
      "exitPrice": 34.52,
      "isLong": false,
      "quantity": 100,
      "entryScore": -60,
      "entryVwapScore": -100,
      "entryEmaScore": -100,
      "entryRsiScore": -13,
      "entryMacdScore": -100,
      "entryAdxScore": -59,
      "entryVolumeScore": 0,
      "rsiAtEntry": 51.49774393964367,
      "adxAtEntry": 23.109252327470557,
      "entryBollingerScore": 0,
      "entryStochasticScore": 0,
      "entryObvScore": 0,
      "entryCciScore": 0,
      "entryWilliamsRScore": 0,
      "entrySentimentScore": 0,
      "entrySentimentConfidence": 0,
      "macdHistogramAtEntry": 0,
      "volumeRatioAtEntry": 0,
      "aboveVwapAtEntry": false,
      "aboveEma9AtEntry": false,
      "aboveEma21AtEntry": false,
      "exitScore": -16,
      "rsiAtExit": 51.49774393964367,
      "adxAtExit": 23.109252327470557,
      "exitReason": "reversal",
      "pnL": -9.000000000000341,
      "pnLPercent": -0.26139994191113397,
      "isWin": false,
      "duration": "00:07:00",
      "entryHour": 10,
      "entryMinute": 57,
      "timeBucket": "10:45"
    },
    {
      "entryTime": "2026-01-26T15:00:00",
      "exitTime": "2026-01-26T15:03:00",
      "entryPrice": 34.94,
      "exitPrice": 35.05,
      "isLong": false,
      "quantity": 100,
      "entryScore": -65,
      "entryVwapScore": -100,
      "entryEmaScore": -100,
      "entryRsiScore": -29,
      "entryMacdScore": -79,
      "entryAdxScore": -48,
      "entryVolumeScore": -79,
      "rsiAtEntry": 50.61988792008291,
      "adxAtEntry": 21.816721069289304,
      "entryBollingerScore": 0,
      "entryStochasticScore": 0,
      "entryObvScore": 0,
      "entryCciScore": 0,
      "entryWilliamsRScore": 0,
      "entrySentimentScore": 0,
      "entrySentimentConfidence": 0,
      "macdHistogramAtEntry": 0,
      "volumeRatioAtEntry": 0,
      "aboveVwapAtEntry": false,
      "aboveEma9AtEntry": false,
      "aboveEma21AtEntry": false,
      "exitScore": -21,
      "rsiAtExit": 50.61988792008291,
      "adxAtExit": 21.816721069289304,
      "exitReason": "reversal",
      "pnL": -10.999999999999943,
      "pnLPercent": -0.31482541499713634,
      "isWin": false,
      "duration": "00:03:00",
      "entryHour": 15,
      "entryMinute": 0,
      "timeBucket": "15:00"
    },
    {
      "entryTime": "2026-01-26T15:40:00",
      "exitTime": "2026-01-26T16:17:00",
      "entryPrice": 34.72,
      "exitPrice": 34.63,
      "isLong": false,
      "quantity": 100,
      "entryScore": -65,
      "entryVwapScore": -100,
      "entryEmaScore": -100,
      "entryRsiScore": -24,
      "entryMacdScore": -83,
      "entryAdxScore": -46,
      "entryVolumeScore": -100,
      "rsiAtEntry": 59.914664118778425,
      "adxAtEntry": 26.31854970582146,
      "entryBollingerScore": 0,
      "entryStochasticScore": 0,
      "entryObvScore": 0,
      "entryCciScore": 0,
      "entryWilliamsRScore": 0,
      "entrySentimentScore": 0,
      "entrySentimentConfidence": 0,
      "macdHistogramAtEntry": 0,
      "volumeRatioAtEntry": 0,
      "aboveVwapAtEntry": false,
      "aboveEma9AtEntry": false,
      "aboveEma21AtEntry": false,
      "exitScore": -13,
      "rsiAtExit": 59.914664118778425,
      "adxAtExit": 26.31854970582146,
      "exitReason": "reversal",
      "pnL": 8.99999999999963,
      "pnLPercent": 0.2592165898617405,
      "isWin": true,
      "duration": "00:37:00",
      "entryHour": 15,
      "entryMinute": 40,
      "timeBucket": "15:30"
    },
    {
      "entryTime": "2026-01-27T12:24:00",
      "exitTime": "2026-01-27T13:04:00",
      "entryPrice": 35.29,
      "exitPrice": 35.46,
      "isLong": false,
      "quantity": 100,
      "entryScore": -50,
      "entryVwapScore": -100,
      "entryEmaScore": -100,
      "entryRsiScore": 16,
      "entryMacdScore": -100,
      "entryAdxScore": -100,
      "entryVolumeScore": 0,
      "rsiAtEntry": 67.54014742507378,
      "adxAtEntry": 33.57845649961568,
      "entryBollingerScore": 0,
      "entryStochasticScore": 0,
      "entryObvScore": 0,
      "entryCciScore": 0,
      "entryWilliamsRScore": 0,
      "entrySentimentScore": 0,
      "entrySentimentConfidence": 0,
      "macdHistogramAtEntry": 0,
      "volumeRatioAtEntry": 0,
      "aboveVwapAtEntry": false,
      "aboveEma9AtEntry": false,
      "aboveEma21AtEntry": false,
      "exitScore": 5,
      "rsiAtExit": 67.54014742507378,
      "adxAtExit": 33.57845649961568,
      "exitReason": "reversal",
      "pnL": -17.00000000000017,
      "pnLPercent": -0.48172286766789946,
      "isWin": false,
      "duration": "00:40:00",
      "entryHour": 12,
      "entryMinute": 24,
      "timeBucket": "12:15"
    },
    {
      "entryTime": "2026-01-28T09:53:00",
      "exitTime": "2026-01-28T10:01:00",
      "entryPrice": 37,
      "exitPrice": 37.07,
      "isLong": false,
      "quantity": 100,
      "entryScore": -65,
      "entryVwapScore": -97,
      "entryEmaScore": -100,
      "entryRsiScore": -31,
      "entryMacdScore": -100,
      "entryAdxScore": -69,
      "entryVolumeScore": 0,
      "rsiAtEntry": 47.50548309480831,
      "adxAtEntry": 36.75197972125233,
      "entryBollingerScore": 0,
      "entryStochasticScore": 0,
      "entryObvScore": 0,
      "entryCciScore": 0,
      "entryWilliamsRScore": 0,
      "entrySentimentScore": 0,
      "entrySentimentConfidence": 0,
      "macdHistogramAtEntry": 0,
      "volumeRatioAtEntry": 0,
      "aboveVwapAtEntry": false,
      "aboveEma9AtEntry": false,
      "aboveEma21AtEntry": false,
      "exitScore": -36,
      "rsiAtExit": 47.50548309480831,
      "adxAtExit": 36.75197972125233,
      "exitReason": "reversal",
      "pnL": -7.000000000000028,
      "pnLPercent": -0.18918918918918998,
      "isWin": false,
      "duration": "00:08:00",
      "entryHour": 9,
      "entryMinute": 53,
      "timeBucket": "09:45"
    },
    {
      "entryTime": "2026-01-28T10:16:00",
      "exitTime": "2026-01-28T10:28:00",
      "entryPrice": 36.6,
      "exitPrice": 36.74,
      "isLong": false,
      "quantity": 100,
      "entryScore": -51,
      "entryVwapScore": -100,
      "entryEmaScore": -100,
      "entryRsiScore": -25,
      "entryMacdScore": -100,
      "entryAdxScore": -87,
      "entryVolumeScore": 0,
      "rsiAtEntry": 49.93723222875595,
      "adxAtEntry": 38.081082791395644,
      "entryBollingerScore": 0,
      "entryStochasticScore": 0,
      "entryObvScore": 0,
      "entryCciScore": 0,
      "entryWilliamsRScore": 0,
      "entrySentimentScore": 0,
      "entrySentimentConfidence": 0,
      "macdHistogramAtEntry": 0,
      "volumeRatioAtEntry": 0,
      "aboveVwapAtEntry": false,
      "aboveEma9AtEntry": false,
      "aboveEma21AtEntry": false,
      "exitScore": -28,
      "rsiAtExit": 49.93723222875595,
      "adxAtExit": 38.081082791395644,
      "exitReason": "reversal",
      "pnL": -14.000000000000057,
      "pnLPercent": -0.3825136612021873,
      "isWin": false,
      "duration": "00:12:00",
      "entryHour": 10,
      "entryMinute": 16,
      "timeBucket": "10:15"
    },
    {
      "entryTime": "2026-01-28T10:29:00",
      "exitTime": "2026-01-28T10:31:00",
      "entryPrice": 36.68,
      "exitPrice": 36.79,
      "isLong": false,
      "quantity": 100,
      "entryScore": -62,
      "entryVwapScore": -100,
      "entryEmaScore": -100,
      "entryRsiScore": -7,
      "entryMacdScore": -86,
      "entryAdxScore": -74,
      "entryVolumeScore": 0,
      "rsiAtEntry": 52.55816466935901,
      "adxAtEntry": 33.07191220162966,
      "entryBollingerScore": 0,
      "entryStochasticScore": 0,
      "entryObvScore": 0,
      "entryCciScore": 0,
      "entryWilliamsRScore": 0,
      "entrySentimentScore": 0,
      "entrySentimentConfidence": 0,
      "macdHistogramAtEntry": 0,
      "volumeRatioAtEntry": 0,
      "aboveVwapAtEntry": false,
      "aboveEma9AtEntry": false,
      "aboveEma21AtEntry": false,
      "exitScore": -34,
      "rsiAtExit": 52.55816466935901,
      "adxAtExit": 33.07191220162966,
      "exitReason": "reversal",
      "pnL": -10.999999999999943,
      "pnLPercent": -0.299890948745909,
      "isWin": false,
      "duration": "00:02:00",
      "entryHour": 10,
      "entryMinute": 29,
      "timeBucket": "10:15"
    },
    {
      "entryTime": "2026-01-28T15:55:00",
      "exitTime": "2026-01-28T15:57:00",
      "entryPrice": 36.96,
      "exitPrice": 37.11,
      "isLong": false,
      "quantity": 100,
      "entryScore": -69,
      "entryVwapScore": -97,
      "entryEmaScore": -100,
      "entryRsiScore": -27,
      "entryMacdScore": -100,
      "entryAdxScore": -53,
      "entryVolumeScore": -100,
      "rsiAtEntry": 54.5418955470424,
      "adxAtEntry": 24.676398662806868,
      "entryBollingerScore": 0,
      "entryStochasticScore": 0,
      "entryObvScore": 0,
      "entryCciScore": 0,
      "entryWilliamsRScore": 0,
      "entrySentimentScore": 0,
      "entrySentimentConfidence": 0,
      "macdHistogramAtEntry": 0,
      "volumeRatioAtEntry": 0,
      "aboveVwapAtEntry": false,
      "aboveEma9AtEntry": false,
      "aboveEma21AtEntry": false,
      "exitScore": -3,
      "rsiAtExit": 54.5418955470424,
      "adxAtExit": 24.676398662806868,
      "exitReason": "reversal",
      "pnL": -14.999999999999858,
      "pnLPercent": -0.405844155844152,
      "isWin": false,
      "duration": "00:02:00",
      "entryHour": 15,
      "entryMinute": 55,
      "timeBucket": "15:45"
    },
    {
      "entryTime": "2026-01-29T09:32:00",
      "exitTime": "2026-01-29T09:47:00",
      "entryPrice": 34.64,
      "exitPrice": 34.26101301300605,
      "isLong": false,
      "quantity": 100,
      "entryScore": -58,
      "entryVwapScore": -100,
      "entryEmaScore": -100,
      "entryRsiScore": 80,
      "entryMacdScore": -96,
      "entryAdxScore": -84,
      "entryVolumeScore": -100,
      "rsiAtEntry": 35.192206737047684,
      "adxAtEntry": 46.23889016461199,
      "entryBollingerScore": 0,
      "entryStochasticScore": 0,
      "entryObvScore": 0,
      "entryCciScore": 0,
      "entryWilliamsRScore": 0,
      "entrySentimentScore": 0,
      "entrySentimentConfidence": 0,
      "macdHistogramAtEntry": 0,
      "volumeRatioAtEntry": 0,
      "aboveVwapAtEntry": false,
      "aboveEma9AtEntry": false,
      "aboveEma21AtEntry": false,
      "exitScore": -55,
      "rsiAtExit": 35.192206737047684,
      "adxAtExit": 46.23889016461199,
      "exitReason": "TP",
      "pnL": 37.898698699395084,
      "pnLPercent": 1.0940732880887725,
      "isWin": true,
      "duration": "00:15:00",
      "entryHour": 9,
      "entryMinute": 32,
      "timeBucket": "09:30"
    },
    {
      "entryTime": "2026-01-29T10:18:00",
      "exitTime": "2026-01-29T10:28:00",
      "entryPrice": 32.19,
      "exitPrice": 32.58,
      "isLong": false,
      "quantity": 100,
      "entryScore": -58,
      "entryVwapScore": -100,
      "entryEmaScore": -100,
      "entryRsiScore": -47,
      "entryMacdScore": -100,
      "entryAdxScore": -100,
      "entryVolumeScore": 0,
      "rsiAtEntry": 46.547182203128244,
      "adxAtEntry": 48.793552636744096,
      "entryBollingerScore": 0,
      "entryStochasticScore": 0,
      "entryObvScore": 0,
      "entryCciScore": 0,
      "entryWilliamsRScore": 0,
      "entrySentimentScore": 0,
      "entrySentimentConfidence": 0,
      "macdHistogramAtEntry": 0,
      "volumeRatioAtEntry": 0,
      "aboveVwapAtEntry": false,
      "aboveEma9AtEntry": false,
      "aboveEma21AtEntry": false,
      "exitScore": -33,
      "rsiAtExit": 46.547182203128244,
      "adxAtExit": 48.793552636744096,
      "exitReason": "reversal",
      "pnL": -39.00000000000006,
      "pnLPercent": -1.211556383970179,
      "isWin": false,
      "duration": "00:10:00",
      "entryHour": 10,
      "entryMinute": 18,
      "timeBucket": "10:15"
    },
    {
      "entryTime": "2026-01-29T10:29:00",
      "exitTime": "2026-01-29T10:41:00",
      "entryPrice": 32.56,
      "exitPrice": 31.725138770444264,
      "isLong": false,
      "quantity": 100,
      "entryScore": -54,
      "entryVwapScore": -100,
      "entryEmaScore": 33,
      "entryRsiScore": -10,
      "entryMacdScore": -100,
      "entryAdxScore": -92,
      "entryVolumeScore": -98,
      "rsiAtEntry": 25.55644885552306,
      "adxAtEntry": 32.32151310438234,
      "entryBollingerScore": 0,
      "entryStochasticScore": 0,
      "entryObvScore": 0,
      "entryCciScore": 0,
      "entryWilliamsRScore": 0,
      "entrySentimentScore": 0,
      "entrySentimentConfidence": 0,
      "macdHistogramAtEntry": 0,
      "volumeRatioAtEntry": 0,
      "aboveVwapAtEntry": false,
      "aboveEma9AtEntry": false,
      "aboveEma21AtEntry": false,
      "exitScore": -50,
      "rsiAtExit": 25.55644885552306,
      "adxAtExit": 32.32151310438234,
      "exitReason": "TP",
      "pnL": 83.4861229555738,
      "pnLPercent": 2.5640701153431755,
      "isWin": true,
      "duration": "00:12:00",
      "entryHour": 10,
      "entryMinute": 29,
      "timeBucket": "10:15"
    },
    {
      "entryTime": "2026-01-29T13:36:00",
      "exitTime": "2026-01-29T13:41:00",
      "entryPrice": 31.58,
      "exitPrice": 31.73,
      "isLong": false,
      "quantity": 100,
      "entryScore": -51,
      "entryVwapScore": -100,
      "entryEmaScore": -33,
      "entryRsiScore": -19,
      "entryMacdScore": -100,
      "entryAdxScore": -91,
      "entryVolumeScore": 0,
      "rsiAtEntry": 50.204616172504565,
      "adxAtEntry": 36.45267413482888,
      "entryBollingerScore": 0,
      "entryStochasticScore": 0,
      "entryObvScore": 0,
      "entryCciScore": 0,
      "entryWilliamsRScore": 0,
      "entrySentimentScore": 0,
      "entrySentimentConfidence": 0,
      "macdHistogramAtEntry": 0,
      "volumeRatioAtEntry": 0,
      "aboveVwapAtEntry": false,
      "aboveEma9AtEntry": false,
      "aboveEma21AtEntry": false,
      "exitScore": -14,
      "rsiAtExit": 50.204616172504565,
      "adxAtExit": 36.45267413482888,
      "exitReason": "reversal",
      "pnL": -15.000000000000213,
      "pnLPercent": -0.47498416719443365,
      "isWin": false,
      "duration": "00:05:00",
      "entryHour": 13,
      "entryMinute": 36,
      "timeBucket": "13:30"
    },
    {
      "entryTime": "2026-01-29T13:46:00",
      "exitTime": "2026-01-29T14:16:00",
      "entryPrice": 31.53,
      "exitPrice": 31.26,
      "isLong": false,
      "quantity": 100,
      "entryScore": -61,
      "entryVwapScore": -100,
      "entryEmaScore": -100,
      "entryRsiScore": -21,
      "entryMacdScore": -100,
      "entryAdxScore": -55,
      "entryVolumeScore": 0,
      "rsiAtEntry": 63.31583276937343,
      "adxAtEntry": 31.337500887334336,
      "entryBollingerScore": 0,
      "entryStochasticScore": 0,
      "entryObvScore": 0,
      "entryCciScore": 0,
      "entryWilliamsRScore": 0,
      "entrySentimentScore": 0,
      "entrySentimentConfidence": 0,
      "macdHistogramAtEntry": 0,
      "volumeRatioAtEntry": 0,
      "aboveVwapAtEntry": false,
      "aboveEma9AtEntry": false,
      "aboveEma21AtEntry": false,
      "exitScore": -5,
      "rsiAtExit": 63.31583276937343,
      "adxAtExit": 31.337500887334336,
      "exitReason": "reversal",
      "pnL": 26.999999999999957,
      "pnLPercent": 0.8563273073263544,
      "isWin": true,
      "duration": "00:30:00",
      "entryHour": 13,
      "entryMinute": 46,
      "timeBucket": "13:45"
    },
    {
      "entryTime": "2026-01-30T13:25:00",
      "exitTime": "2026-01-30T13:40:00",
      "entryPrice": 28.38,
      "exitPrice": 28.74,
      "isLong": false,
      "quantity": 100,
      "entryScore": -57,
      "entryVwapScore": -100,
      "entryEmaScore": -100,
      "entryRsiScore": -47,
      "entryMacdScore": -100,
      "entryAdxScore": -99,
      "entryVolumeScore": 0,
      "rsiAtEntry": 49.444510988213295,
      "adxAtEntry": 23.249197794443226,
      "entryBollingerScore": 0,
      "entryStochasticScore": 0,
      "entryObvScore": 0,
      "entryCciScore": 0,
      "entryWilliamsRScore": 0,
      "entrySentimentScore": 0,
      "entrySentimentConfidence": 0,
      "macdHistogramAtEntry": 0,
      "volumeRatioAtEntry": 0,
      "aboveVwapAtEntry": false,
      "aboveEma9AtEntry": false,
      "aboveEma21AtEntry": false,
      "exitScore": -6,
      "rsiAtExit": 49.444510988213295,
      "adxAtExit": 23.249197794443226,
      "exitReason": "reversal",
      "pnL": -35.99999999999994,
      "pnLPercent": -1.2684989429175457,
      "isWin": false,
      "duration": "00:15:00",
      "entryHour": 13,
      "entryMinute": 25,
      "timeBucket": "13:15"
    },
    {
      "entryTime": "2026-01-30T15:14:00",
      "exitTime": "2026-01-30T15:56:00",
      "entryPrice": 29.75,
      "exitPrice": 29.09,
      "isLong": false,
      "quantity": 100,
      "entryScore": -67,
      "entryVwapScore": -100,
      "entryEmaScore": -100,
      "entryRsiScore": -40,
      "entryMacdScore": -100,
      "entryAdxScore": -69,
      "entryVolumeScore": -75,
      "rsiAtEntry": 50.91108191658839,
      "adxAtEntry": 27.966002306499075,
      "entryBollingerScore": 0,
      "entryStochasticScore": 0,
      "entryObvScore": 0,
      "entryCciScore": 0,
      "entryWilliamsRScore": 0,
      "entrySentimentScore": 0,
      "entrySentimentConfidence": 0,
      "macdHistogramAtEntry": 0,
      "volumeRatioAtEntry": 0,
      "aboveVwapAtEntry": false,
      "aboveEma9AtEntry": false,
      "aboveEma21AtEntry": false,
      "exitScore": -19,
      "rsiAtExit": 50.91108191658839,
      "adxAtExit": 27.966002306499075,
      "exitReason": "reversal",
      "pnL": 66.00000000000001,
      "pnLPercent": 2.2184873949579837,
      "isWin": true,
      "duration": "00:42:00",
      "entryHour": 15,
      "entryMinute": 14,
      "timeBucket": "15:00"
    },
    {
      "entryTime": "2026-02-02T10:05:00",
      "exitTime": "2026-02-02T10:09:00",
      "entryPrice": 21.37,
      "exitPrice": 21.73,
      "isLong": false,
      "quantity": 100,
      "entryScore": -61,
      "entryVwapScore": -100,
      "entryEmaScore": -100,
      "entryRsiScore": -17,
      "entryMacdScore": -100,
      "entryAdxScore": -52,
      "entryVolumeScore": 0,
      "rsiAtEntry": 57.062749009793926,
      "adxAtEntry": 23.259964436393922,
      "entryBollingerScore": 0,
      "entryStochasticScore": 0,
      "entryObvScore": 0,
      "entryCciScore": 0,
      "entryWilliamsRScore": 0,
      "entrySentimentScore": 0,
      "entrySentimentConfidence": 0,
      "macdHistogramAtEntry": 0,
      "volumeRatioAtEntry": 0,
      "aboveVwapAtEntry": false,
      "aboveEma9AtEntry": false,
      "aboveEma21AtEntry": false,
      "exitScore": 0,
      "rsiAtExit": 57.062749009793926,
      "adxAtExit": 23.259964436393922,
      "exitReason": "reversal",
      "pnL": -35.99999999999994,
      "pnLPercent": -1.6846045858680367,
      "isWin": false,
      "duration": "00:04:00",
      "entryHour": 10,
      "entryMinute": 5,
      "timeBucket": "10:00"
    },
    {
      "entryTime": "2026-02-02T11:53:00",
      "exitTime": "2026-02-02T12:01:00",
      "entryPrice": 21.97,
      "exitPrice": 22.3,
      "isLong": false,
      "quantity": 100,
      "entryScore": -63,
      "entryVwapScore": -100,
      "entryEmaScore": -100,
      "entryRsiScore": -41,
      "entryMacdScore": -100,
      "entryAdxScore": -52,
      "entryVolumeScore": -51,
      "rsiAtEntry": 59.039691112351946,
      "adxAtEntry": 24.796403296312057,
      "entryBollingerScore": 0,
      "entryStochasticScore": 0,
      "entryObvScore": 0,
      "entryCciScore": 0,
      "entryWilliamsRScore": 0,
      "entrySentimentScore": 0,
      "entrySentimentConfidence": 0,
      "macdHistogramAtEntry": 0,
      "volumeRatioAtEntry": 0,
      "aboveVwapAtEntry": false,
      "aboveEma9AtEntry": false,
      "aboveEma21AtEntry": false,
      "exitScore": 1,
      "rsiAtExit": 59.039691112351946,
      "adxAtExit": 24.796403296312057,
      "exitReason": "reversal",
      "pnL": -33.000000000000185,
      "pnLPercent": -1.5020482476103862,
      "isWin": false,
      "duration": "00:08:00",
      "entryHour": 11,
      "entryMinute": 53,
      "timeBucket": "11:45"
    },
    {
      "entryTime": "2026-02-02T12:46:00",
      "exitTime": "2026-02-02T13:24:00",
      "entryPrice": 21.91,
      "exitPrice": 21.72,
      "isLong": false,
      "quantity": 100,
      "entryScore": -63,
      "entryVwapScore": -100,
      "entryEmaScore": -100,
      "entryRsiScore": -35,
      "entryMacdScore": -100,
      "entryAdxScore": -50,
      "entryVolumeScore": 0,
      "rsiAtEntry": 48.19871061509588,
      "adxAtEntry": 21.916920572616,
      "entryBollingerScore": 0,
      "entryStochasticScore": 0,
      "entryObvScore": 0,
      "entryCciScore": 0,
      "entryWilliamsRScore": 0,
      "entrySentimentScore": 0,
      "entrySentimentConfidence": 0,
      "macdHistogramAtEntry": 0,
      "volumeRatioAtEntry": 0,
      "aboveVwapAtEntry": false,
      "aboveEma9AtEntry": false,
      "aboveEma21AtEntry": false,
      "exitScore": -9,
      "rsiAtExit": 48.19871061509588,
      "adxAtExit": 21.916920572616,
      "exitReason": "reversal",
      "pnL": 19.000000000000128,
      "pnLPercent": 0.8671839342765919,
      "isWin": true,
      "duration": "00:38:00",
      "entryHour": 12,
      "entryMinute": 46,
      "timeBucket": "12:45"
    },
    {
      "entryTime": "2026-02-03T10:14:00",
      "exitTime": "2026-02-03T10:21:00",
      "entryPrice": 20,
      "exitPrice": 20.18,
      "isLong": false,
      "quantity": 100,
      "entryScore": -66,
      "entryVwapScore": -100,
      "entryEmaScore": -100,
      "entryRsiScore": -26,
      "entryMacdScore": -94,
      "entryAdxScore": -33,
      "entryVolumeScore": -100,
      "rsiAtEntry": 50.48416340807164,
      "adxAtEntry": 14.695237827594095,
      "entryBollingerScore": 0,
      "entryStochasticScore": 0,
      "entryObvScore": 0,
      "entryCciScore": 0,
      "entryWilliamsRScore": 0,
      "entrySentimentScore": 0,
      "entrySentimentConfidence": 0,
      "macdHistogramAtEntry": 0,
      "volumeRatioAtEntry": 0,
      "aboveVwapAtEntry": false,
      "aboveEma9AtEntry": false,
      "aboveEma21AtEntry": false,
      "exitScore": -14,
      "rsiAtExit": 50.48416340807164,
      "adxAtExit": 14.695237827594095,
      "exitReason": "reversal",
      "pnL": -17.99999999999997,
      "pnLPercent": -0.8999999999999986,
      "isWin": false,
      "duration": "00:07:00",
      "entryHour": 10,
      "entryMinute": 14,
      "timeBucket": "10:00"
    },
    {
      "entryTime": "2026-02-03T11:28:00",
      "exitTime": "2026-02-03T12:22:00",
      "entryPrice": 20.04,
      "exitPrice": 19.54,
      "isLong": false,
      "quantity": 100,
      "entryScore": -66,
      "entryVwapScore": -100,
      "entryEmaScore": -100,
      "entryRsiScore": -34,
      "entryMacdScore": -100,
      "entryAdxScore": -61,
      "entryVolumeScore": -24,
      "rsiAtEntry": 52.582370290058236,
      "adxAtEntry": 31.79025338632911,
      "entryBollingerScore": 0,
      "entryStochasticScore": 0,
      "entryObvScore": 0,
      "entryCciScore": 0,
      "entryWilliamsRScore": 0,
      "entrySentimentScore": 0,
      "entrySentimentConfidence": 0,
      "macdHistogramAtEntry": 0,
      "volumeRatioAtEntry": 0,
      "aboveVwapAtEntry": false,
      "aboveEma9AtEntry": false,
      "aboveEma21AtEntry": false,
      "exitScore": -6,
      "rsiAtExit": 52.582370290058236,
      "adxAtExit": 31.79025338632911,
      "exitReason": "reversal",
      "pnL": 50,
      "pnLPercent": 2.4950099800399204,
      "isWin": true,
      "duration": "00:54:00",
      "entryHour": 11,
      "entryMinute": 28,
      "timeBucket": "11:15"
    },
    {
      "entryTime": "2026-02-03T12:26:00",
      "exitTime": "2026-02-03T13:18:00",
      "entryPrice": 19.42,
      "exitPrice": 18.391258280366944,
      "isLong": false,
      "quantity": 100,
      "entryScore": -62,
      "entryVwapScore": -100,
      "entryEmaScore": -100,
      "entryRsiScore": -14,
      "entryMacdScore": -88,
      "entryAdxScore": -50,
      "entryVolumeScore": -68,
      "rsiAtEntry": 28.851151374585342,
      "adxAtEntry": 39.13964690595922,
      "entryBollingerScore": 0,
      "entryStochasticScore": 0,
      "entryObvScore": 0,
      "entryCciScore": 0,
      "entryWilliamsRScore": 0,
      "entrySentimentScore": 0,
      "entrySentimentConfidence": 0,
      "macdHistogramAtEntry": 0,
      "volumeRatioAtEntry": 0,
      "aboveVwapAtEntry": false,
      "aboveEma9AtEntry": false,
      "aboveEma21AtEntry": false,
      "exitScore": -54,
      "rsiAtExit": 28.851151374585342,
      "adxAtExit": 39.13964690595922,
      "exitReason": "TP",
      "pnL": 102.87417196330573,
      "pnLPercent": 5.297331203053847,
      "isWin": true,
      "duration": "00:52:00",
      "entryHour": 12,
      "entryMinute": 26,
      "timeBucket": "12:15"
    },
    {
      "entryTime": "2026-02-03T13:32:00",
      "exitTime": "2026-02-03T14:05:00",
      "entryPrice": 17.8,
      "exitPrice": 17.63,
      "isLong": false,
      "quantity": 100,
      "entryScore": -71,
      "entryVwapScore": -100,
      "entryEmaScore": -100,
      "entryRsiScore": -43,
      "entryMacdScore": -100,
      "entryAdxScore": -100,
      "entryVolumeScore": 0,
      "rsiAtEntry": 51.654440819484535,
      "adxAtEntry": 23.72117497937965,
      "entryBollingerScore": 0,
      "entryStochasticScore": 0,
      "entryObvScore": 0,
      "entryCciScore": 0,
      "entryWilliamsRScore": 0,
      "entrySentimentScore": 0,
      "entrySentimentConfidence": 0,
      "macdHistogramAtEntry": 0,
      "volumeRatioAtEntry": 0,
      "aboveVwapAtEntry": false,
      "aboveEma9AtEntry": false,
      "aboveEma21AtEntry": false,
      "exitScore": -21,
      "rsiAtExit": 51.654440819484535,
      "adxAtExit": 23.72117497937965,
      "exitReason": "reversal",
      "pnL": 17.00000000000017,
      "pnLPercent": 0.9550561797752904,
      "isWin": true,
      "duration": "00:33:00",
      "entryHour": 13,
      "entryMinute": 32,
      "timeBucket": "13:30"
    },
    {
      "entryTime": "2026-02-04T13:20:00",
      "exitTime": "2026-02-04T13:27:00",
      "entryPrice": 16.88,
      "exitPrice": 17.14,
      "isLong": false,
      "quantity": 100,
      "entryScore": -63,
      "entryVwapScore": -100,
      "entryEmaScore": -100,
      "entryRsiScore": -20,
      "entryMacdScore": -100,
      "entryAdxScore": -57,
      "entryVolumeScore": -16,
      "rsiAtEntry": 54.86442037541593,
      "adxAtEntry": 22.01225558098334,
      "entryBollingerScore": 0,
      "entryStochasticScore": 0,
      "entryObvScore": 0,
      "entryCciScore": 0,
      "entryWilliamsRScore": 0,
      "entrySentimentScore": 0,
      "entrySentimentConfidence": 0,
      "macdHistogramAtEntry": 0,
      "volumeRatioAtEntry": 0,
      "aboveVwapAtEntry": false,
      "aboveEma9AtEntry": false,
      "aboveEma21AtEntry": false,
      "exitScore": 0,
      "rsiAtExit": 54.86442037541593,
      "adxAtExit": 22.01225558098334,
      "exitReason": "reversal",
      "pnL": -26.000000000000156,
      "pnLPercent": -1.5402843601895828,
      "isWin": false,
      "duration": "00:07:00",
      "entryHour": 13,
      "entryMinute": 20,
      "timeBucket": "13:15"
    },
    {
      "entryTime": "2026-02-05T10:15:00",
      "exitTime": "2026-02-05T10:34:00",
      "entryPrice": 15.56,
      "exitPrice": 14.286520480288234,
      "isLong": false,
      "quantity": 100,
      "entryScore": -58,
      "entryVwapScore": -100,
      "entryEmaScore": -100,
      "entryRsiScore": -44,
      "entryMacdScore": -100,
      "entryAdxScore": -85,
      "entryVolumeScore": -45,
      "rsiAtEntry": 26.573702476434036,
      "adxAtEntry": 44.77858154985326,
      "entryBollingerScore": 0,
      "entryStochasticScore": 0,
      "entryObvScore": 0,
      "entryCciScore": 0,
      "entryWilliamsRScore": 0,
      "entrySentimentScore": 0,
      "entrySentimentConfidence": 0,
      "macdHistogramAtEntry": 0,
      "volumeRatioAtEntry": 0,
      "aboveVwapAtEntry": false,
      "aboveEma9AtEntry": false,
      "aboveEma21AtEntry": false,
      "exitScore": -50,
      "rsiAtExit": 26.573702476434036,
      "adxAtExit": 44.77858154985326,
      "exitReason": "TP",
      "pnL": 127.3479519711767,
      "pnLPercent": 8.184315679381536,
      "isWin": true,
      "duration": "00:19:00",
      "entryHour": 10,
      "entryMinute": 15,
      "timeBucket": "10:15"
    },
    {
      "entryTime": "2026-02-05T10:46:00",
      "exitTime": "2026-02-05T10:51:00",
      "entryPrice": 14.56,
      "exitPrice": 15.15,
      "isLong": false,
      "quantity": 100,
      "entryScore": -61,
      "entryVwapScore": -100,
      "entryEmaScore": -100,
      "entryRsiScore": -28,
      "entryMacdScore": -100,
      "entryAdxScore": -50,
      "entryVolumeScore": 0,
      "rsiAtEntry": 61.35734454117473,
      "adxAtEntry": 22.33453413402555,
      "entryBollingerScore": 0,
      "entryStochasticScore": 0,
      "entryObvScore": 0,
      "entryCciScore": 0,
      "entryWilliamsRScore": 0,
      "entrySentimentScore": 0,
      "entrySentimentConfidence": 0,
      "macdHistogramAtEntry": 0,
      "volumeRatioAtEntry": 0,
      "aboveVwapAtEntry": false,
      "aboveEma9AtEntry": false,
      "aboveEma21AtEntry": false,
      "exitScore": 0,
      "rsiAtExit": 61.35734454117473,
      "adxAtExit": 22.33453413402555,
      "exitReason": "reversal",
      "pnL": -58.999999999999986,
      "pnLPercent": -4.052197802197801,
      "isWin": false,
      "duration": "00:05:00",
      "entryHour": 10,
      "entryMinute": 46,
      "timeBucket": "10:45"
    },
    {
      "entryTime": "2026-02-05T15:28:00",
      "exitTime": "2026-02-05T15:58:00",
      "entryPrice": 13.4,
      "exitPrice": 13.2,
      "isLong": false,
      "quantity": 100,
      "entryScore": -61,
      "entryVwapScore": -100,
      "entryEmaScore": -100,
      "entryRsiScore": -33,
      "entryMacdScore": -100,
      "entryAdxScore": -74,
      "entryVolumeScore": 0,
      "rsiAtEntry": 54.95908511715635,
      "adxAtEntry": 32.50500011320733,
      "entryBollingerScore": 0,
      "entryStochasticScore": 0,
      "entryObvScore": 0,
      "entryCciScore": 0,
      "entryWilliamsRScore": 0,
      "entrySentimentScore": 0,
      "entrySentimentConfidence": 0,
      "macdHistogramAtEntry": 0,
      "volumeRatioAtEntry": 0,
      "aboveVwapAtEntry": false,
      "aboveEma9AtEntry": false,
      "aboveEma21AtEntry": false,
      "exitScore": -11,
      "rsiAtExit": 54.95908511715635,
      "adxAtExit": 32.50500011320733,
      "exitReason": "reversal",
      "pnL": 20.000000000000107,
      "pnLPercent": 1.4925373134328437,
      "isWin": true,
      "duration": "00:30:00",
      "entryHour": 15,
      "entryMinute": 28,
      "timeBucket": "15:15"
    },
    {
      "entryTime": "2026-02-06T13:11:00",
      "exitTime": "2026-02-06T13:35:00",
      "entryPrice": 15.68,
      "exitPrice": 15.77,
      "isLong": false,
      "quantity": 100,
      "entryScore": -60,
      "entryVwapScore": -100,
      "entryEmaScore": -100,
      "entryRsiScore": -43,
      "entryMacdScore": -100,
      "entryAdxScore": -53,
      "entryVolumeScore": 0,
      "rsiAtEntry": 57.97223090562423,
      "adxAtEntry": 19.868684030491057,
      "entryBollingerScore": 0,
      "entryStochasticScore": 0,
      "entryObvScore": 0,
      "entryCciScore": 0,
      "entryWilliamsRScore": 0,
      "entrySentimentScore": 0,
      "entrySentimentConfidence": 0,
      "macdHistogramAtEntry": 0,
      "volumeRatioAtEntry": 0,
      "aboveVwapAtEntry": false,
      "aboveEma9AtEntry": false,
      "aboveEma21AtEntry": false,
      "exitScore": 0,
      "rsiAtExit": 57.97223090562423,
      "adxAtExit": 19.868684030491057,
      "exitReason": "reversal",
      "pnL": -8.999999999999986,
      "pnLPercent": -0.5739795918367337,
      "isWin": false,
      "duration": "00:24:00",
      "entryHour": 13,
      "entryMinute": 11,
      "timeBucket": "13:00"
    },
    {
      "entryTime": "2026-02-06T15:21:00",
      "exitTime": "2026-02-06T15:28:00",
      "entryPrice": 15.77,
      "exitPrice": 15.87,
      "isLong": false,
      "quantity": 100,
      "entryScore": -61,
      "entryVwapScore": -100,
      "entryEmaScore": -100,
      "entryRsiScore": -33,
      "entryMacdScore": -83,
      "entryAdxScore": -55,
      "entryVolumeScore": 0,
      "rsiAtEntry": 52.06851275708085,
      "adxAtEntry": 23.901122628410725,
      "entryBollingerScore": 0,
      "entryStochasticScore": 0,
      "entryObvScore": 0,
      "entryCciScore": 0,
      "entryWilliamsRScore": 0,
      "entrySentimentScore": 0,
      "entrySentimentConfidence": 0,
      "macdHistogramAtEntry": 0,
      "volumeRatioAtEntry": 0,
      "aboveVwapAtEntry": false,
      "aboveEma9AtEntry": false,
      "aboveEma21AtEntry": false,
      "exitScore": -15,
      "rsiAtExit": 52.06851275708085,
      "adxAtExit": 23.901122628410725,
      "exitReason": "reversal",
      "pnL": -9.999999999999964,
      "pnLPercent": -0.6341154090044366,
      "isWin": false,
      "duration": "00:07:00",
      "entryHour": 15,
      "entryMinute": 21,
      "timeBucket": "15:15"
    }
  ],
  "totalTrades": 62,
  "totalWins": 24,
  "totalLosses": 38,
  "totalProfit": 983.6799249048345,
  "totalLoss": -765.702068964686,
  "longTrades": 2,
  "longWins": 1,
  "shortTrades": 60,
  "shortWins": 23,
  "winRate": 38.70967741935484,
  "longWinRate": 50,
  "shortWinRate": 38.333333333333336,
  "profitFactor": 1.2846771149970624,
  "totalPnL": 217.97785594014852,
  "longEntryThresholdStats": {
    "65": {
      "threshold": 65,
      "totalTrades": 1,
      "wins": 0,
      "losses": 1,
      "totalProfit": 0,
      "totalLoss": -10.000000000000142,
      "winRate": 0,
      "profitFactor": 0,
      "averageWin": 0,
      "averageLoss": -10.000000000000142,
      "expectancy": -10.000000000000142
    },
    "60": {
      "threshold": 60,
      "totalTrades": 1,
      "wins": 1,
      "losses": 0,
      "totalProfit": 10.000000000000142,
      "totalLoss": 0,
      "winRate": 100,
      "profitFactor": 999,
      "averageWin": 10.000000000000142,
      "averageLoss": 0,
      "expectancy": 10.000000000000142
    }
  },
  "shortEntryThresholdStats": {
    "-50": {
      "threshold": -50,
      "totalTrades": 7,
      "wins": 1,
      "losses": 6,
      "totalProfit": 83.4861229555738,
      "totalLoss": -112.00000000000152,
      "winRate": 14.285714285714285,
      "profitFactor": 0.7454118121033274,
      "averageWin": 83.4861229555738,
      "averageLoss": -18.66666666666692,
      "expectancy": -4.0734110063468165
    },
    "-60": {
      "threshold": -60,
      "totalTrades": 26,
      "wins": 9,
      "losses": 17,
      "totalProfit": 266.8741719633056,
      "totalLoss": -369.70206896468466,
      "winRate": 34.61538461538461,
      "profitFactor": 0.7218628035019151,
      "averageWin": 29.652685773700625,
      "averageLoss": -21.747180527334393,
      "expectancy": -3.954919115437655
    },
    "-65": {
      "threshold": -65,
      "totalTrades": 18,
      "wins": 8,
      "losses": 10,
      "totalProfit": 385.90749879976056,
      "totalLoss": -158.99999999999963,
      "winRate": 44.44444444444444,
      "profitFactor": 2.4270911874198835,
      "averageWin": 48.23843734997007,
      "averageLoss": -15.899999999999963,
      "expectancy": 12.605972155542274
    },
    "-55": {
      "threshold": -55,
      "totalTrades": 7,
      "wins": 4,
      "losses": 3,
      "totalProfit": 220.4121311861943,
      "totalLoss": -82.00000000000003,
      "winRate": 57.14285714285714,
      "profitFactor": 2.687952819343832,
      "averageWin": 55.103032796548575,
      "averageLoss": -27.333333333333343,
      "expectancy": 19.77316159802775
    },
    "-70": {
      "threshold": -70,
      "totalTrades": 2,
      "wins": 1,
      "losses": 1,
      "totalProfit": 17.00000000000017,
      "totalLoss": -32.99999999999983,
      "winRate": 50,
      "profitFactor": 0.515151515151523,
      "averageWin": 17.00000000000017,
      "averageLoss": -32.99999999999983,
      "expectancy": -7.9999999999998295
    }
  },
  "exitScoreStats": {
    "-35": {
      "threshold": -35,
      "totalTrades": 7,
      "wins": 2,
      "losses": 5,
      "totalProfit": 30.999999999999517,
      "totalLoss": -60.00000000000085,
      "winRate": 28.57142857142857,
      "profitFactor": 0.5166666666666513,
      "averageWin": 15.499999999999758,
      "averageLoss": -12.00000000000017,
      "expectancy": -4.142857142857333
    },
    "-25": {
      "threshold": -25,
      "totalTrades": 9,
      "wins": 3,
      "losses": 6,
      "totalProfit": 57.99999999999983,
      "totalLoss": -99.99999999999929,
      "winRate": 33.33333333333333,
      "profitFactor": 0.5800000000000024,
      "averageWin": 19.333333333333275,
      "averageLoss": -16.666666666666547,
      "expectancy": -4.666666666666607
    },
    "0": {
      "threshold": 0,
      "totalTrades": 10,
      "wins": 0,
      "losses": 10,
      "totalProfit": 0,
      "totalLoss": -321.1707575857382,
      "winRate": 0,
      "profitFactor": 0,
      "averageWin": 0,
      "averageLoss": -32.11707575857382,
      "expectancy": -32.11707575857382
    },
    "-20": {
      "threshold": -20,
      "totalTrades": 6,
      "wins": 3,
      "losses": 3,
      "totalProfit": 71.00000000000009,
      "totalLoss": -18.999999999999773,
      "winRate": 50,
      "profitFactor": 3.7368421052632073,
      "averageWin": 23.666666666666696,
      "averageLoss": -6.3333333333332575,
      "expectancy": 8.66666666666672
    },
    "-30": {
      "threshold": -30,
      "totalTrades": 4,
      "wins": 1,
      "losses": 3,
      "totalProfit": 10.000000000000142,
      "totalLoss": -64.00000000000006,
      "winRate": 25,
      "profitFactor": 0.15625000000000208,
      "averageWin": 10.000000000000142,
      "averageLoss": -21.333333333333353,
      "expectancy": -13.499999999999979
    },
    "-5": {
      "threshold": -5,
      "totalTrades": 6,
      "wins": 4,
      "losses": 2,
      "totalProfit": 96.99999999999989,
      "totalLoss": -42.00000000000017,
      "winRate": 66.66666666666666,
      "profitFactor": 2.3095238095237973,
      "averageWin": 24.24999999999997,
      "averageLoss": -21.000000000000085,
      "expectancy": 9.16666666666662
    },
    "-10": {
      "threshold": -10,
      "totalTrades": 5,
      "wins": 2,
      "losses": 3,
      "totalProfit": 28.999999999999737,
      "totalLoss": -54.00000000000027,
      "winRate": 40,
      "profitFactor": 0.5370370370370294,
      "averageWin": 14.499999999999869,
      "averageLoss": -18.00000000000009,
      "expectancy": -5.000000000000107
    },
    "35": {
      "threshold": 35,
      "totalTrades": 1,
      "wins": 0,
      "losses": 1,
      "totalProfit": 0,
      "totalLoss": -10.000000000000142,
      "winRate": 0,
      "profitFactor": 0,
      "averageWin": 0,
      "averageLoss": -10.000000000000142,
      "expectancy": -10.000000000000142
    },
    "15": {
      "threshold": 15,
      "totalTrades": 1,
      "wins": 1,
      "losses": 0,
      "totalProfit": 10.000000000000142,
      "totalLoss": 0,
      "winRate": 100,
      "profitFactor": 999,
      "averageWin": 10.000000000000142,
      "averageLoss": 0,
      "expectancy": 10.000000000000142
    },
    "-50": {
      "threshold": -50,
      "totalTrades": 4,
      "wins": 4,
      "losses": 0,
      "totalProfit": 422.9190253045214,
      "totalLoss": 0,
      "winRate": 100,
      "profitFactor": 999,
      "averageWin": 105.72975632613036,
      "averageLoss": 0,
      "expectancy": 105.72975632613036
    },
    "-55": {
      "threshold": -55,
      "totalTrades": 3,
      "wins": 3,
      "losses": 0,
      "totalProfit": 188.7608996003138,
      "totalLoss": 0,
      "winRate": 100,
      "profitFactor": 999,
      "averageWin": 62.920299866771266,
      "averageLoss": 0,
      "expectancy": 62.920299866771266
    },
    "-15": {
      "threshold": -15,
      "totalTrades": 4,
      "wins": 1,
      "losses": 3,
      "totalProfit": 66.00000000000001,
      "totalLoss": -36.000000000000476,
      "winRate": 25,
      "profitFactor": 1.8333333333333095,
      "averageWin": 66.00000000000001,
      "averageLoss": -12.000000000000158,
      "expectancy": 7.4999999999998845
    },
    "5": {
      "threshold": 5,
      "totalTrades": 2,
      "wins": 0,
      "losses": 2,
      "totalProfit": 0,
      "totalLoss": -59.53131137894658,
      "winRate": 0,
      "profitFactor": 0,
      "averageWin": 0,
      "averageLoss": -29.76565568947329,
      "expectancy": -29.76565568947329
    }
  },
  "timeWindowStats": {
    "13:00": {
      "timeBucket": "13:00",
      "totalTrades": 3,
      "wins": 0,
      "totalProfit": -58.000000000000895,
      "winRate": 0,
      "averageProfit": -19.33333333333363
    },
    "09:30": {
      "timeBucket": "09:30",
      "totalTrades": 9,
      "wins": 4,
      "totalProfit": -67.63788974966687,
      "winRate": 44.44444444444444,
      "averageProfit": -7.515321083296318
    },
    "10:00": {
      "timeBucket": "10:00",
      "totalTrades": 5,
      "wins": 2,
      "totalProfit": 72.21077841446473,
      "winRate": 40,
      "averageProfit": 14.442155682892945
    },
    "12:45": {
      "timeBucket": "12:45",
      "totalTrades": 4,
      "wins": 1,
      "totalProfit": -26.999999999999247,
      "winRate": 25,
      "averageProfit": -6.749999999999812
    },
    "15:15": {
      "timeBucket": "15:15",
      "totalTrades": 4,
      "wins": 1,
      "totalProfit": -36.999999999999744,
      "winRate": 25,
      "averageProfit": -9.249999999999936
    },
    "15:00": {
      "timeBucket": "15:00",
      "totalTrades": 3,
      "wins": 1,
      "totalProfit": 41.000000000000014,
      "winRate": 33.33333333333333,
      "averageProfit": 13.666666666666671
    },
    "12:15": {
      "timeBucket": "12:15",
      "totalTrades": 4,
      "wins": 2,
      "totalProfit": 95.8741719633057,
      "winRate": 50,
      "averageProfit": 23.968542990826425
    },
    "14:15": {
      "timeBucket": "14:15",
      "totalTrades": 3,
      "wins": 3,
      "totalProfit": 48.0000000000004,
      "winRate": 100,
      "averageProfit": 16.00000000000013
    },
    "15:45": {
      "timeBucket": "15:45",
      "totalTrades": 2,
      "wins": 0,
      "totalProfit": -21.000000000000085,
      "winRate": 0,
      "averageProfit": -10.500000000000043
    },
    "12:30": {
      "timeBucket": "12:30",
      "totalTrades": 2,
      "wins": 0,
      "totalProfit": -36.999999999999744,
      "winRate": 0,
      "averageProfit": -18.499999999999872
    },
    "11:30": {
      "timeBucket": "11:30",
      "totalTrades": 1,
      "wins": 0,
      "totalProfit": -10.000000000000142,
      "winRate": 0,
      "averageProfit": -10.000000000000142
    },
    "11:45": {
      "timeBucket": "11:45",
      "totalTrades": 3,
      "wins": 1,
      "totalProfit": -21.00000000000044,
      "winRate": 33.33333333333333,
      "averageProfit": -7.0000000000001465
    },
    "11:15": {
      "timeBucket": "11:15",
      "totalTrades": 2,
      "wins": 2,
      "totalProfit": 164.69672038529595,
      "winRate": 100,
      "averageProfit": 82.34836019264797
    },
    "15:30": {
      "timeBucket": "15:30",
      "totalTrades": 3,
      "wins": 2,
      "totalProfit": 13.999999999999346,
      "winRate": 66.66666666666666,
      "averageProfit": 4.6666666666664485
    },
    "10:30": {
      "timeBucket": "10:30",
      "totalTrades": 1,
      "wins": 1,
      "totalProfit": 21.999999999999886,
      "winRate": 100,
      "averageProfit": 21.999999999999886
    },
    "10:45": {
      "timeBucket": "10:45",
      "totalTrades": 2,
      "wins": 0,
      "totalProfit": -68.00000000000033,
      "winRate": 0,
      "averageProfit": -34.00000000000016
    },
    "09:45": {
      "timeBucket": "09:45",
      "totalTrades": 1,
      "wins": 0,
      "totalProfit": -7.000000000000028,
      "winRate": 0,
      "averageProfit": -7.000000000000028
    },
    "10:15": {
      "timeBucket": "10:15",
      "totalTrades": 5,
      "wins": 2,
      "totalProfit": 146.83407492675045,
      "winRate": 40,
      "averageProfit": 29.36681498535009
    },
    "13:30": {
      "timeBucket": "13:30",
      "totalTrades": 2,
      "wins": 1,
      "totalProfit": 1.9999999999999574,
      "winRate": 50,
      "averageProfit": 0.9999999999999787
    },
    "13:45": {
      "timeBucket": "13:45",
      "totalTrades": 1,
      "wins": 1,
      "totalProfit": 26.999999999999957,
      "winRate": 100,
      "averageProfit": 26.999999999999957
    },
    "13:15": {
      "timeBucket": "13:15",
      "totalTrades": 2,
      "wins": 0,
      "totalProfit": -62.0000000000001,
      "winRate": 0,
      "averageProfit": -31.00000000000005
    }
  },
  "indicatorCorrelations": [
    {
      "indicatorName": "RSI",
      "condition": "Bearish (30-50)",
      "occurrences": 20,
      "wins": 9,
      "totalProfit": -3.1013013006063517,
      "winRate": 45,
      "averageProfit": -0.15506506503031758
    },
    {
      "indicatorName": "ADX",
      "condition": "Very Strong (\u003E=40)",
      "occurrences": 11,
      "wins": 6,
      "totalProfit": 208.5775401925435,
      "winRate": 54.54545454545454,
      "averageProfit": 18.9615945629585
    },
    {
      "indicatorName": "MACD",
      "condition": "Strong Bearish (\u003C-50)",
      "occurrences": 60,
      "wins": 23,
      "totalProfit": 217.97785594014871,
      "winRate": 38.333333333333336,
      "averageProfit": 3.632964265669145
    },
    {
      "indicatorName": "VWAP",
      "condition": "Well Below (bearish)",
      "occurrences": 60,
      "wins": 23,
      "totalProfit": 217.97785594014871,
      "winRate": 38.333333333333336,
      "averageProfit": 3.632964265669145
    },
    {
      "indicatorName": "EMA",
      "condition": "Bearish Stack (below all)",
      "occurrences": 57,
      "wins": 22,
      "totalProfit": 176.49173298457546,
      "winRate": 38.59649122807017,
      "averageProfit": 3.09634619271185
    },
    {
      "indicatorName": "RSI",
      "condition": "Bullish (50-70)",
      "occurrences": 36,
      "wins": 9,
      "totalProfit": -352.7020689646851,
      "winRate": 25,
      "averageProfit": -9.797279693463475
    },
    {
      "indicatorName": "ADX",
      "condition": "Strong Trend (\u003E=25)",
      "occurrences": 33,
      "wins": 15,
      "totalProfit": 295.40031574760536,
      "winRate": 45.45454545454545,
      "averageProfit": 8.951524719624405
    },
    {
      "indicatorName": "EMA",
      "condition": "Bearish Bias",
      "occurrences": 2,
      "wins": 0,
      "totalProfit": -42.000000000000526,
      "winRate": 0,
      "averageProfit": -21.000000000000263
    },
    {
      "indicatorName": "Volume",
      "condition": "Low (\u003Cavg)",
      "occurrences": 24,
      "wins": 13,
      "totalProfit": 351.28113555485464,
      "winRate": 54.166666666666664,
      "averageProfit": 14.636713981452276
    },
    {
      "indicatorName": "ADX",
      "condition": "Weak Trend (\u003C25)",
      "occurrences": 18,
      "wins": 3,
      "totalProfit": -286.0000000000001,
      "winRate": 16.666666666666664,
      "averageProfit": -15.888888888888895
    },
    {
      "indicatorName": "MACD",
      "condition": "Strong Bullish (\u003E50)",
      "occurrences": 2,
      "wins": 1,
      "totalProfit": 0,
      "winRate": 50,
      "averageProfit": 0
    },
    {
      "indicatorName": "Volume",
      "condition": "Very High (\u003E2x avg)",
      "occurrences": 2,
      "wins": 1,
      "totalProfit": 0,
      "winRate": 50,
      "averageProfit": 0
    },
    {
      "indicatorName": "VWAP",
      "condition": "Well Above (bullish)",
      "occurrences": 2,
      "wins": 1,
      "totalProfit": 0,
      "winRate": 50,
      "averageProfit": 0
    },
    {
      "indicatorName": "EMA",
      "condition": "Bullish Stack (above all)",
      "occurrences": 2,
      "wins": 1,
      "totalProfit": 0,
      "winRate": 50,
      "averageProfit": 0
    },
    {
      "indicatorName": "RSI",
      "condition": "Oversold (\u003C=30)",
      "occurrences": 6,
      "wins": 6,
      "totalProfit": 573.7812262054401,
      "winRate": 100,
      "averageProfit": 95.63020436757336
    },
    {
      "indicatorName": "EMA",
      "condition": "Bullish Bias",
      "occurrences": 1,
      "wins": 1,
      "totalProfit": 83.4861229555738,
      "winRate": 100,
      "averageProfit": 83.4861229555738
    }
  ],
  "optimalLongEntryThreshold": 65,
  "optimalShortEntryThreshold": -55,
  "optimalLongExitThreshold": 40,
  "optimalShortExitThreshold": -40,
  "confidence": 100,
  "averageTradeDurationMinutes": 15.064516129032258,
  "averageWinAmount": 40.98666353770144,
  "averageLossAmount": -20.150054446439103,
  "bestTradeProfit": 127.3479519711767,
  "worstTradeLoss": -63.17075758573765,
  "currentStreak": -2,
  "longestWinStreak": 3,
  "longestLossStreak": 5,
  "bestHours": [],
  "avoidHours": [],
  "lastSentimentScore": 0,
  "lastSentimentConfidence": 0,
  "lastSentimentUpdate": "0001-01-01T00:00:00"
}